Workbook

Sheet 合约状态
A1: 合约类型 | B1: 合约编号 | C1: 名义本金 | D1: 挂钩标的 | E1: 起始日期 | F1: 期初价格 | G1: 敲入点位 | H1: 敲入距离 | I1: 距离敲出线 | J1: 下一敲出观察 | K1: 下一敲出票息率 | L1: 下次敲出票息 | M1: 次级票息 | N1: 距离合约结束 | O1: 了结日期 | P1: DATE | Q1: SPOT | R1: NPV | S1: DELTA | T1: GAMMA | U1: VEGA | V1: THETA | W1: RHO | X1: RHO Q | Y1: RISK FREE RATE | Z1: CARRY COST | AA1: VOLATILITY | AB1: 已了结收益 | AC1: 期初价格 | AD1: 起息日 | AE1: 敲入障碍价格 | AF1: 每日观察敲入 | AG1: 敲入执行价格 | AH1: 敲入参与率 | AI1: 是否已敲入 | AJ1: 红利票息 | AK1: 保证金比例 | AL1: 最大亏损比例 | AM1: 昨日NPV | AN1: 敲出观察 | AP1: 敲出障碍 | AR1: 派息观察日 | AT1: 派息月息
A2: SNB | B2: 19 | C2: 23000000 | D2: 000852.SH | E2: 46111.625 | F2: 7767.9297 | G2: =F2*AE2 -> 5437.5508 | H2: =实时行情!$E$7 /( 合约状态!F2 *合约状态!AE2)-1 -> 0.47092548 | I2: {=TRANSPOSE(_xll.DistanceToNearestBarrier(P2,Q2,F2,AN2:BI2,BJ2:CE2))} -> -0.028794151 | J2: 46203 | K2: 0.33 | L2: =(J2-AD2)/365*C2*K2 -> 1900099.3 | M2: 0.1 | N2: =BI2-P2 -> 719.375 | P2: =实时行情!$A$2 -> 46122.625 | Q2: =实时行情!E7 -> 7998.232 | R2: {=TRANSPOSE(_xll.ValuateSnowball(实时行情!$D$1,F2,E2,AN2:BI2,BJ2:CE2,CF2:DA2,0,AJ2,AE2,AG2,AH2,AK2,AL2,0,0,0,TRUE,AF2,P2,Q2,Y2,Z2,AA2,AI2,"ALL")*C2/F2)} -> 698825.59 | S2: 2069.8467 | T2: -2.6669 | U2: -12479628 | V2: 4477089.1 | W2: -14609096 | X2: -16377378 | Y2: 0.021 | Z2: -0.0746 | AA2: 0.179 | AB2: 0 | AC2: 7767.93 | AD2: 46111.625 | AE2: 0.7 | AF2: TRUE | AG2: 1 | AH2: 1 | AI2: FALSE | AJ2: 0.1 | AK2: 1 | AL2: 1 | AM2: {=IF(ISERROR(TRANSPOSE(_xll.ValuateSnowball(实时行情!$D$1,F2,AD2,AN2:BI2,BJ2:CE2,CF2:DA2,0,AJ2,AE2,AG2,AH2,AK2,AL2,0,0,0,TRUE,AF2,实时行情!$B$2,实时行情!E8,Y2,Z2,AA2,FALSE,"NPV")*C2/F2)), 0, TRANSPOSE(_xll.ValuateSnowball(实时行情!$D$1,F2,AD2,AN2:BI2,BJ2:CE2,CF2:DA2,0,AJ2,AE2,AG2,AH2,AK2,AL2,0,0,0,TRUE,AF2,实时行情!$B$2,实时行情!$E$8,Y2,Z2,AA2,FALSE,"NPV")*C2/F2))} -> 513106.12 | AN2: 46203 | AO2: 46233 | AP2: 46265 | AQ2: 46295 | AR2: 46325 | AS2: 46356 | AT2: 46386 | AU2: 46416 | AV2: 46444 | AW2: 46476 | AX2: 46507 | AY2: 46538 | AZ2: 46568 | BA2: 46598 | BB2: 46629 | BC2: 46660 | BD2: 46689 | BE2: 46721 | BF2: 46751 | BG2: 46776 | BH2: 46812 | BI2: 46842 | BJ2: 1 | BK2: 1 | BL2: 1 | BM2: 1 | BN2: 1 | BO2: 1 | BP2: 1 | BQ2: 1 | BR2: 1 | BS2: 1 | BT2: 1 | BU2: 1 | BV2: 1 | BW2: 1 | BX2: 1 | BY2: 1 | BZ2: 1 | CA2: 1 | CB2: 1 | CC2: 1 | CD2: 1 | CE2: 1 | CF2: 0.33 | CG2: 0.33 | CH2: 0.33 | CI2: 0.33 | CJ2: 0.33 | CK2: 0.33 | CL2: 0.33 | CM2: 0.33 | CN2: 0.33 | CO2: 0.33 | CP2: 0.1 | CQ2: 0.1 | CR2: 0.1 | CS2: 0.1 | CT2: 0.1 | CU2: 0.1 | CV2: 0.1 | CW2: 0.1 | CX2: 0.1 | CY2: 0.1 | CZ2: 0.1 | DA2: 0.1
A3: SNB | B3: 18 | C3: 11000000 | D3: 000852.SH | E3: 46079.625 | F3: 8490.62 | G3: =F3*AE3 -> 5943.434 | H3: =实时行情!$E$7 /( 合约状态!F3 *合约状态!AE3)-1 -> 0.34572572 | I3: {=TRANSPOSE(_xll.DistanceToNearestBarrier(P3,Q3,F3,AN3:BI3,BJ3:CE3))} -> 0.061562105 | J3: 46168 | K3: 0.1971 | L3: =(J3-AD3)/365*C3*K3 -> 524947.5 | M3: 0.1971 | N3: =BI3-P3 -> 688.375 | P3: =实时行情!$A$2 -> 46122.625 | Q3: =实时行情!E7 -> 7998.232 | R3: {=TRANSPOSE(_xll.ValuateSnowball(实时行情!$D$1,F3,AD3,AN3:BI3,BJ3:CE3,CF3:DA3,0,AJ3,AE3,AG3,AH3,AK3,AL3,0,0,0,TRUE,AF3,P3,Q3,Y3,Z3,AA3,FALSE,"ALL")*C3/F3)} -> -224424.15 | S3: 1159.5029 | T3: -1.1016718 | U3: -11216115 | V3: 2036904.5 | W3: -10667322 | X3: -13048952 | Y3: 0.021 | Z3: -0.05783 | AA3: 0.19 | AB3: 0 | AC3: 8490.62 | AD3: 46079.625 | AE3: 0.7 | AF3: TRUE | AG3: 1 | AH3: 1 | AI3: FALSE | AJ3: 0.1971 | AK3: 1 | AL3: 1 | AM3: {=IF(ISERROR(TRANSPOSE(_xll.ValuateSnowball(实时行情!$D$1,F3,AD3,AN3:BI3,BJ3:CE3,CF3:DA3,0,AJ3,AE3,AG3,AH3,AK3,AL3,0,0,0,TRUE,AF3,实时行情!$B$2,实时行情!E8,Y3,Z3,AA3,FALSE,"NPV")*C3/F3)), 0, TRANSPOSE(_xll.ValuateSnowball(实时行情!$D$1,F3,AD3,AN3:BI3,BJ3:CE3,CF3:DA3,0,AJ3,AE3,AG3,AH3,AK3,AL3,0,0,0,TRUE,AF3,实时行情!$B$2,实时行情!$E$8,Y3,Z3,AA3,FALSE,"NPV")*C3/F3))} -> -325040.11 | AN3: 46168 | AO3: 46199 | AP3: 46230 | AQ3: 46260 | AR3: 46293 | AS3: 46321 | AT3: 46352 | AU3: 46384 | AV3: 46413 | AW3: 46444 | AX3: 46472 | AY3: 46503 | AZ3: 46533 | BA3: 46566 | BB3: 46594 | BC3: 46625 | BD3: 46657 | BE3: 46686 | BF3: 46717 | BG3: 46748 | BH3: 46776 | BI3: 46811 | BJ3: 1 | BK3: 1 | BL3: 1 | BM3: 1 | BN3: 1 | BO3: 1 | BP3: 1 | BQ3: 1 | BR3: 1 | BS3: 1 | BT3: 1 | BU3: 1 | BV3: 1 | BW3: 1 | BX3: 1 | BY3: 1 | BZ3: 1 | CA3: 1 | CB3: 1 | CC3: 1 | CD3: 1 | CE3: 1 | CF3: 0.1971 | CG3: 0.1971 | CH3: 0.1971 | CI3: 0.1971 | CJ3: 0.1971 | CK3: 0.1971 | CL3: 0.1971 | CM3: 0.1971 | CN3: 0.1971 | CO3: 0.1971 | CP3: 0.1971 | CQ3: 0.1971 | CR3: 0.1971 | CS3: 0.1971 | CT3: 0.1971 | CU3: 0.1971 | CV3: 0.1971 | CW3: 0.1971 | CX3: 0.1971 | CY3: 0.1971 | CZ3: 0.1971 | DA3: 0.1971
A4: SNB | B4: 17 | C4: 12000000 | D4: 000852.SH | E4: 46078.625 | F4: 8426.33 | G4: =F4*AE4 -> 5898.431 | H4: =实时行情!$E$7 /( 合约状态!F4 *合约状态!AE4)-1 -> 0.35599314 | I4: {=TRANSPOSE(_xll.DistanceToNearestBarrier(P4,Q4,F4,AN4:BI4,BJ4:CE4))} -> 0.053524079 | J4: 46167 | K4: 0.34 | L4: =(J4-AD4)/365*C4*K4 -> 987863.01 | M4: 0.05 | N4: =BI4-P4 -> 685.375 | P4: =实时行情!$A$2 -> 46122.625 | Q4: =实时行情!E7 -> 7998.232 | R4: {=TRANSPOSE(_xll.ValuateSnowball(实时行情!$D$1,F4,AD4,AN4:BI4,BJ4:CE4,CF4:DA4,0,AJ4,AE4,AG4,AH4,AK4,AL4,0,0,0,TRUE,AF4,P4,Q4,Y4,Z4,AA4,FALSE,"ALL")*C4/F4)} -> -385397.81 | S4: 1919.3828 | T4: -1.0040957 | U4: -4868184.5 | V4: 2263621.3 | W4: -10798897 | X4: -14427163 | Y4: 0.021 | Z4: -0.06378 | AA4: 0.18 | AB4: 0 | AC4: 8426.33 | AD4: 46078.625 | AE4: 0.7 | AF4: TRUE | AG4: 1 | AH4: 1 | AI4: FALSE | AJ4: 0.05 | AK4: 1 | AL4: 1 | AM4: {=IF(ISERROR(TRANSPOSE(_xll.ValuateSnowball(实时行情!$D$1,F4,AD4,AN4:BI4,BJ4:CE4,CF4:DA4,0,AJ4,AE4,AG4,AH4,AK4,AL4,0,0,0,TRUE,AF4,实时行情!$B$2,实时行情!E8,Y4,Z4,AA4,FALSE,"NPV")*C4/F4)), 0, TRANSPOSE(_xll.ValuateSnowball(实时行情!$D$1,F4,AD4,AN4:BI4,BJ4:CE4,CF4:DA4,0,AJ4,AE4,AG4,AH4,AK4,AL4,0,0,0,TRUE,AF4,实时行情!$B$2,实时行情!$E$8,Y4,Z4,AA4,FALSE,"NPV")*C4/F4))} -> -544399.68 | AN4: 46167 | AO4: 46198 | AP4: 46230 | AQ4: 46259 | AR4: 46293 | AS4: 46321 | AT4: 46351 | AU4: 46381 | AV4: 46412 | AW4: 46443 | AX4: 46471 | AY4: 46503 | AZ4: 46532 | BA4: 46563 | BB4: 46594 | BC4: 46624 | BD4: 46657 | BE4: 46685 | BF4: 46716 | BG4: 46748 | BH4: 46776 | BI4: 46808 | BJ4: 1 | BK4: 1 | BL4: 1 | BM4: 1 | BN4: 1 | BO4: 1 | BP4: 1 | BQ4: 1 | BR4: 1 | BS4: 1 | BT4: 1 | BU4: 1 | BV4: 1 | BW4: 1 | BX4: 1 | BY4: 1 | BZ4: 1 | CA4: 1 | CB4: 1 | CC4: 1 | CD4: 1 | CE4: 1 | CF4: 0.34 | CG4: 0.34 | CH4: 0.34 | CI4: 0.34 | CJ4: 0.34 | CK4: 0.34 | CL4: 0.34 | CM4: 0.34 | CN4: 0.34 | CO4: 0.34 | CP4: 0.05 | CQ4: 0.05 | CR4: 0.05 | CS4: 0.05 | CT4: 0.05 | CU4: 0.05 | CV4: 0.05 | CW4: 0.05 | CX4: 0.05 | CY4: 0.05 | CZ4: 0.05 | DA4: 0.05
A5: SNB | B5: 16 | C5: 21000000 | D5: 000852.SH | E5: 46058.625 | F5: 8091.49 | G5: =F5*AE5 -> 5259.4685 | H5: =实时行情!$E$7 /( 合约状态!F5 *合约状态!AE5)-1 -> 0.52073009 | I5: {=TRANSPOSE(_xll.DistanceToNearestBarrier(P5,Q5,F5,AN5:BI5,BJ5:CE5))} -> 0.011659827 | J5: 46148 | K5: 0.1769 | L5: =(J5-AD5)/365*C5*K5 -> 909641.61 | M5: 0.1769 | N5: =BI5-P5 -> 667.375 | P5: =实时行情!$A$2 -> 46122.625 | Q5: =实时行情!E7 -> 7998.232 | R5: {=TRANSPOSE(_xll.ValuateSnowball(实时行情!$D$1,F5,AD5,AN5:BI5,BJ5:CE5,CF5:DA5,0,AJ5,AE5,AG5,AH5,AK5,AL5,0,0,0,TRUE,AF5,P5,Q5,Y5,Z5,AA5,FALSE,"ALL")*C5/F5)} -> 472107.07 | S5: 1224.2823 | T5: -2.3694666 | U5: -17826180 | V5: 4075029.6 | W5: -13757998 | X5: -14533190 | Y5: 0.021 | Z5: -0.08849 | AA5: 0.19 | AB5: 0 | AC5: 8091.49 | AD5: 46058.625 | AE5: 0.65 | AF5: TRUE | AG5: 1 | AH5: 1 | AI5: FALSE | AJ5: 0.1769 | AK5: 1 | AL5: 1 | AM5: {=IF(ISERROR(TRANSPOSE(_xll.ValuateSnowball(实时行情!$D$1,F5,AD5,AN5:BI5,BJ5:CE5,CF5:DA5,0,AJ5,AE5,AG5,AH5,AK5,AL5,0,0,0,TRUE,AF5,实时行情!$B$2,实时行情!E8,Y5,Z5,AA5,FALSE,"NPV")*C5/F5)), 0, TRANSPOSE(_xll.ValuateSnowball(实时行情!$D$1,F5,AD5,AN5:BI5,BJ5:CE5,CF5:DA5,0,AJ5,AE5,AG5,AH5,AK5,AL5,0,0,0,TRUE,AF5,实时行情!$B$2,实时行情!$E$8,Y5,Z5,AA5,FALSE,"NPV")*C5/F5))} -> 353766.28 | AN5: 46148 | AO5: 46178 | AP5: 46209 | AQ5: 46239 | AR5: 46272 | AS5: 46303 | AT5: 46331 | AU5: 46363 | AV5: 46392 | AW5: 46433 | AX5: 46451 | AY5: 46483 | AZ5: 46513 | BA5: 46545 | BB5: 46573 | BC5: 46604 | BD5: 46636 | BE5: 46668 | BF5: 46696 | BG5: 46727 | BH5: 46757 | BI5: 46790 | BJ5: 1 | BK5: 1 | BL5: 1 | BM5: 1 | BN5: 1 | BO5: 1 | BP5: 1 | BQ5: 1 | BR5: 1 | BS5: 1 | BT5: 1 | BU5: 1 | BV5: 1 | BW5: 1 | BX5: 1 | BY5: 1 | BZ5: 1 | CA5: 1 | CB5: 1 | CC5: 1 | CD5: 1 | CE5: 1 | CF5: 0.1769 | CG5: 0.1769 | CH5: 0.1769 | CI5: 0.1769 | CJ5: 0.1769 | CK5: 0.1769 | CL5: 0.1769 | CM5: 0.1769 | CN5: 0.1769 | CO5: 0.1769 | CP5: 0.1769 | CQ5: 0.1769 | CR5: 0.1769 | CS5: 0.1769 | CT5: 0.1769 | CU5: 0.1769 | CV5: 0.1769 | CW5: 0.1769 | CX5: 0.1769 | CY5: 0.1769 | CZ5: 0.1769 | DA5: 0.1769
A6: SNB | B6: 15 | C6: 21000000 | D6: 000852.SH | E6: 46049.625 | F6: 8272.2 | G6: =F6*AE6 -> 5376.93 | H6: =实时行情!$E$7 /( 合约状态!F6 *合约状态!AE6)-1 -> 0.48750904 | I6: {=TRANSPOSE(_xll.DistanceToNearestBarrier(P6,Q6,F6,AN6:BI6,BJ6:CE6))} -> 0.03425357 | J6: 46139 | K6: 0.25 | L6: =(J6-AD6)/365*C6*K6 -> 1285530.8 | M6: 0.05 | N6: =BI6-P6 -> 653.375 | P6: =实时行情!$A$2 -> 46122.625 | Q6: =实时行情!E7 -> 7998.232 | R6: {=TRANSPOSE(_xll.ValuateSnowball(实时行情!$D$1,F6,AD6,AN6:BI6,BJ6:CE6,CF6:DA6,0,AJ6,AE6,AG6,AH6,AK6,AL6,0,0,0,TRUE,AF6,P6,Q6,Y6,Z6,AA6,FALSE,"ALL")*C6/F6)} -> 137586.54 | S6: 2651.8782 | T6: -2.201965 | U6: -13262509 | V6: 4031604.8 | W6: -17048116 | X6: -18567228 | Y6: 0.021 | Z6: -0.074075 | AA6: 0.17 | AB6: 0 | AC6: 8272.2 | AD6: 46049.625 | AE6: 0.65 | AF6: TRUE | AG6: 1 | AH6: 1 | AI6: FALSE | AJ6: 0.05 | AK6: 1 | AL6: 1 | AM6: {=IF(ISERROR(TRANSPOSE(_xll.ValuateSnowball(实时行情!$D$1,F6,AD6,AN6:BI6,BJ6:CE6,CF6:DA6,0,AJ6,AE6,AG6,AH6,AK6,AL6,0,0,0,TRUE,AF6,实时行情!$B$2,实时行情!E8,Y6,Z6,AA6,FALSE,"NPV")*C6/F6)), 0, TRANSPOSE(_xll.ValuateSnowball(实时行情!$D$1,F6,AD6,AN6:BI6,BJ6:CE6,CF6:DA6,0,AJ6,AE6,AG6,AH6,AK6,AL6,0,0,0,TRUE,AF6,实时行情!$B$2,实时行情!$E$8,Y6,Z6,AA6,FALSE,"NPV")*C6/F6))} -> -87731.505 | AN6: 46139 | AO6: 46169 | AP6: 46202 | AQ6: 46230 | AR6: 46261 | AS6: 46293 | AT6: 46322 | AU6: 46353 | AV6: 46384 | AW6: 46414 | AX6: 46444 | AY6: 46475 | AZ6: 46504 | BA6: 46534 | BB6: 46566 | BC6: 46595 | BD6: 46626 | BE6: 46657 | BF6: 46687 | BG6: 46720 | BH6: 46748 | BI6: 46776 | BJ6: 1 | BK6: 1 | BL6: 1 | BM6: 1 | BN6: 1 | BO6: 1 | BP6: 1 | BQ6: 1 | BR6: 1 | BS6: 1 | BT6: 1 | BU6: 1 | BV6: 1 | BW6: 1 | BX6: 1 | BY6: 1 | BZ6: 1 | CA6: 1 | CB6: 1 | CC6: 1 | CD6: 1 | CE6: 1 | CF6: 0.25 | CG6: 0.25 | CH6: 0.25 | CI6: 0.25 | CJ6: 0.25 | CK6: 0.25 | CL6: 0.25 | CM6: 0.25 | CN6: 0.25 | CO6: 0.25 | CP6: 0.05 | CQ6: 0.05 | CR6: 0.05 | CS6: 0.05 | CT6: 0.05 | CU6: 0.05 | CV6: 0.05 | CW6: 0.05 | CX6: 0.05 | CY6: 0.05 | CZ6: 0.05 | DA6: 0.05
A7: SNB | B7: 14 | C7: 10000000 | D7: 000852.SH | E7: 46035.625 | F7: 8287.81 | G7: =F7*AE7 -> 5387.0765 | H7: =实时行情!$E$7 /( 合约状态!F7 *合约状态!AE7)-1 -> 0.48470734 | I7: {=TRANSPOSE(_xll.DistanceToNearestBarrier(P7,Q7,F7,AN7:BI7,BJ7:CE7))} -> 0.036205251 | J7: 46125 | K7: 0.2584 | L7: =(J7-AD7)/365*C7*K7 -> 632726.03 | M7: 0.05 | N7: =BI7-P7 -> 642.375 | P7: =实时行情!$A$2 -> 46122.625 | Q7: =实时行情!E7 -> 7998.232 | R7: {=TRANSPOSE(_xll.ValuateSnowball(实时行情!$D$1,F7,AD7,AN7:BI7,BJ7:CE7,CF7:DA7,0,AJ7,AE7,AG7,AH7,AK7,AL7,0,0,0,TRUE,AF7,P7,Q7,Y7,Z7,AA7,FALSE,"ALL")*C7/F7)} -> 163460.25 | S7: 1299.5901 | T7: -0.97027908 | U7: -5106577.6 | V7: 2203143.5 | W7: -1107932.3 | X7: -8646945 | Y7: 0.021 | Z7: -0.0889946 | AA7: 0.185 | AB7: 0 | AC7: 8287.81 | AD7: 46035.625 | AE7: 0.65 | AF7: TRUE | AG7: 1 | AH7: 1 | AI7: FALSE | AJ7: 0.05 | AK7: 0.25 | AL7: 1 | AM7: {=IF(ISERROR(TRANSPOSE(_xll.ValuateSnowball(实时行情!$D$1,F7,AD7,AN7:BI7,BJ7:CE7,CF7:DA7,0,AJ7,AE7,AG7,AH7,AK7,AL7,0,0,0,TRUE,AF7,实时行情!$B$2,实时行情!E8,Y7,Z7,AA7,FALSE,"NPV")*C7/F7)), 0, TRANSPOSE(_xll.ValuateSnowball(实时行情!$D$1,F7,AD7,AN7:BI7,BJ7:CE7,CF7:DA7,0,AJ7,AE7,AG7,AH7,AK7,AL7,0,0,0,TRUE,AF7,实时行情!$B$2,实时行情!$E$8,Y7,Z7,AA7,FALSE,"NPV")*C7/F7))} -> 52236.702 | AN7: 46125 | AO7: 46155 | AP7: 46188 | AQ7: 46216 | AR7: 46247 | AS7: 46279 | AT7: 46308 | AU7: 46339 | AV7: 46370 | AW7: 46400 | AX7: 46433 | AY7: 46461 | AZ7: 46490 | BA7: 46520 | BB7: 46552 | BC7: 46581 | BD7: 46612 | BE7: 46643 | BF7: 46673 | BG7: 46706 | BH7: 46734 | BI7: 46765 | BJ7: 1 | BK7: 0.995 | BL7: 0.99 | BM7: 0.985 | BN7: 0.98 | BO7: 0.975 | BP7: 0.97 | BQ7: 0.965 | BR7: 0.96 | BS7: 0.955 | BT7: 0.95 | BU7: 0.945 | BV7: 0.94 | BW7: 0.935 | BX7: 0.93 | BY7: 0.925 | BZ7: 0.92 | CA7: 0.915 | CB7: 0.91 | CC7: 0.905 | CD7: 0.9 | CE7: 0.895 | CF7: 0.2584 | CG7: 0.2584 | CH7: 0.2584 | CI7: 0.2584 | CJ7: 0.2584 | CK7: 0.2584 | CL7: 0.2584 | CM7: 0.2584 | CN7: 0.2584 | CO7: 0.2584 | CP7: 0.05 | CQ7: 0.05 | CR7: 0.05 | CS7: 0.05 | CT7: 0.05 | CU7: 0.05 | CV7: 0.05 | CW7: 0.05 | CX7: 0.05 | CY7: 0.05 | CZ7: 0.05 | DA7: 0.05
A8: SNB | B8: 13 | C8: 30000000 | D8: 000852.SH | E8: 46031.625 | F8: 8080.6 | G8: =F8*AE8 -> 5252.39 | H8: =实时行情!$E$7 /( 合约状态!F8 *合约状态!AE8)-1 -> 0.52277953 | I8: {=TRANSPOSE(_xll.DistanceToNearestBarrier(P8,Q8,F8,AN8:BI8,BJ8:CE8))} -> 0.0052467845 | J8: 46153 | K8: 0.275 | L8: =(J8-AD8)/365*C8*K8 -> 2743407.5 | M8: 0.05 | N8: =BI8-P8 -> 639.375 | P8: =实时行情!$A$2 -> 46122.625 | Q8: =实时行情!E7 -> 7998.232 | R8: {=TRANSPOSE(_xll.ValuateSnowball(实时行情!$D$1,F8,AD8,AN8:BI8,BJ8:CE8,CF8:DA8,0,AJ8,AE8,AG8,AH8,AK8,AL8,0,0,0,TRUE,AF8,P8,Q8,Y8,Z8,AA8,FALSE,"ALL")*C8/F8)} -> 1391417.3 | S8: 3364.2096 | T8: -4.8192495 | U8: -13522661 | V8: 8009419.9 | W8: -14950355 | X8: -18418310 | Y8: 0.021 | Z8: -0.08111 | AA8: 0.182 | AB8: 0 | AC8: 8080.6 | AD8: 46031.625 | AE8: 0.65 | AF8: TRUE | AG8: 1 | AH8: 1 | AI8: FALSE | AJ8: 0.05 | AK8: 1 | AL8: 1 | AM8: {=TRANSPOSE(_xll.ValuateSnowball(实时行情!$D$1,F8,AD8,AN8:BI8,BJ8:CE8,CF8:DA8,0,AJ8,AE8,AG8,AH8,AK8,AL8,0,0,0,TRUE,AF8,实时行情!$B$2,实时行情!E8,Y8,Z8,AA8,FALSE,"NPV")*C8/F8)} -> 1087082.5 | AN8: 46121 | AO8: 46153 | AP8: 46182 | AQ8: 46212 | AR8: 46244 | AS8: 46274 | AT8: 46304 | AU8: 46335 | AV8: 46365 | AW8: 46398 | AX8: 46433 | AY8: 46455 | AZ8: 46486 | BA8: 46517 | BB8: 46548 | BC8: 46577 | BD8: 46608 | BE8: 46639 | BF8: 46671 | BG8: 46700 | BH8: 46730 | BI8: 46762 | BJ8: 1 | BK8: 0.995 | BL8: 0.99 | BM8: 0.985 | BN8: 0.98 | BO8: 0.975 | BP8: 0.97 | BQ8: 0.965 | BR8: 0.96 | BS8: 0.955 | BT8: 0.95 | BU8: 0.945 | BV8: 0.94 | BW8: 0.935 | BX8: 0.93 | BY8: 0.925 | BZ8: 0.92 | CA8: 0.915 | CB8: 0.91 | CC8: 0.905 | CD8: 0.9 | CE8: 0.895 | CF8: 0.275 | CG8: 0.275 | CH8: 0.275 | CI8: 0.275 | CJ8: 0.275 | CK8: 0.275 | CL8: 0.275 | CM8: 0.275 | CN8: 0.275 | CO8: 0.275 | CP8: 0.05 | CQ8: 0.05 | CR8: 0.05 | CS8: 0.05 | CT8: 0.05 | CU8: 0.05 | CV8: 0.05 | CW8: 0.05 | CX8: 0.05 | CY8: 0.05 | CZ8: 0.05 | DA8: 0.05

Sheet 实时行情
A1: 实时观察 | B1: 上一交易日 | D1: D:\Quotation\China
A2: =IF(NOW()>TODAY()+0.625, TODAY()+0.625, NOW()) -> 46122.625 | B2: {=_xll.GetNextBusinessDate(D1,TODAY(),-1)+0.625} -> 46121.625
A5: 标的 | B5: 中证 50 | C5: 沪深300 | D5: 中证500 | E5: 中证1000
B6: 000016.SH | C6: 000300.SH | D6: 000905.SH | E6: 000852.SH
A7: 当前点位 | B7: =RTD("em.rtq",,B6,"NOW") -> 2899.579 | C7: =RTD("em.rtq",,C6,"NOW") -> 4636.565 | D7: =RTD("em.rtq",,D6,"NOW") -> 7969.364 | E7: =RTD("em.rtq",,E6,"NOW") -> 7998.232
A8: 昨日收盘 | B8: {=[1]!EM_I_DQ_CLOSE(B6,实时行情!$B$2)} -> 2884.76 | C8: {=[1]!EM_I_DQ_CLOSE(C6,实时行情!$B$2)} -> 4566.2237 | D8: {=[1]!EM_I_DQ_CLOSE(D6,实时行情!$B$2)} -> 7898.6329 | E8: {=[1]!EM_I_DQ_CLOSE(E6,实时行情!$B$2)} -> 7921.4465
A9: 存续估值 | G9: 合计
A11: 昨日估值 | B11: =SUMIF(合约状态!$D:$D,B6,合约状态!$AM:$AM) -> 0 | C11: =SUMIF(合约状态!$D:$D,C6,合约状态!$AM:$AM) -> 0 | D11: =SUMIF(合约状态!$D:$D,D6,合约状态!$AM:$AM) -> 0 | E11: =SUMIF(合约状态!$D:$D,E6,合约状态!$AM:$AM)+ SUMIF(合约状态!$D:$D,E6,合约状态!$AB:$AB) -> 1049020.3 | G11: =SUM(B11:E11) -> 1049020.3
A12: 当日估值 | B12: =SUMIF(合约状态!$D:$D,B6,合约状态!$R:$R) -> 0 | C12: =SUMIF(合约状态!$D:$D,C6,合约状态!$R:$R) -> 0 | D12: =SUMIF(合约状态!$D:$D,D6,合约状态!$R:$R) -> 0 | E12: =SUMIF(合约状态!$D:$D,E6,合约状态!$R:$R)+ SUMIF(合约状态!$D:$D,E6,合约状态!$AB:$AB) -> 2253574.8 | G12: =SUM(B12:E12) -> 2253574.8
A13: 当日盈亏 | B13: =B12-B11 -> 0 | C13: =C12-C11 -> 0 | D13: =D12-D11 -> 0 | E13: =E12-E11 -> 1204554.5 | G13: =SUM(B13:E13) -> 1204554.5
A16: 敲出线上总名本 | B16: =SUMIFS(合约状态!$C:$C,合约状态!$I:$I,"<0",合约状态!$D:$D,B6) -> 0 | C16: =SUMIFS(合约状态!$C:$C,合约状态!$I:$I,"<0",合约状态!$D:$D,C6) -> 0 | D16: =SUMIFS(合约状态!$C:$C,合约状态!$I:$I,"<0",合约状态!$D:$D,D6) -> 0 | E16: =SUMIFS(合约状态!$C:$C,合约状态!$I:$I,"<0",合约状态!$D:$D,E6) -> 23000000 | G16: =SUM(B16:E16) -> 23000000
A17: 敲出线下总名本 | B17: =SUMIFS(合约状态!$C:$C,合约状态!$I:$I,">0",合约状态!$D:$D,B6) -> 0 | C17: =SUMIFS(合约状态!$C:$C,合约状态!$I:$I,">0",合约状态!$D:$D,C6) -> 0 | D17: =SUMIFS(合约状态!$C:$C,合约状态!$I:$I,">0",合约状态!$D:$D,D6) -> 0 | E17: =SUMIFS(合约状态!$C:$C,合约状态!$I:$I,">0",合约状态!$D:$D,E6) -> 105000000 | G17: =SUM(B17:E17) -> 105000000
A19: 标的 | B19: 中证 50 | C19: 沪深300 | D19: 中证500 | E19: 中证1000 | G19: 合计
A20: GREEKS | B20: =SUMIF(合约状态!$D:$D,B6,合约状态!$S:$S) -> 0 | C20: =SUMIF(合约状态!$D:$D,C6,合约状态!$S:$S) -> 0 | D20: =SUMIF(合约状态!$D:$D,D6,合约状态!$S:$S) -> 0 | E20: =SUMIF(合约状态!$D:$D,E6,合约状态!$S:$S) -> 13688.693
A21: NPV | B21: 0 | C21: 0 | D21: 0 | E21: -975660.29 | G21: -975660.29
A23: DELTACASH | B23: =B20*B7 -> 0 | C23: =C20*C7 -> 0 | D23: =D20*D7 -> 0 | E23: =E20*E7 -> 1.0948534e+08 | G23: =SUM(B23:E23) -> 1.0948534e+08
A24: GAMMA | B24: =SUMIF(合约状态!$D:$D,B6,合约状态!$T:$T) -> 0 | C24: =SUMIF(合约状态!$D:$D,C6,合约状态!$T:$T) -> 0 | D24: =SUMIF(合约状态!$D:$D,D6,合约状态!$T:$T) -> 0 | E24: =SUMIF(合约状态!$D:$D,E6,合约状态!$T:$T) -> -15.133628 | F24: （风险度） | G24: =G23/(G16+G17) -> 0.85535421
A25: 1% GAMMACASH | B25: =B24*B7 -> 0 | C25: =C24*C7 -> 0 | D25: =D24*D7 -> 0 | E25: =E24*E7*E7*0.01 -> -9681241.1 | G25: =SUM(B25:E25) -> -9681241.1
A27: 1Day THETA | B27: =SUMIF(合约状态!$D:$D,B6,合约状态!$V:$V) -> 0 | C27: =SUMIF(合约状态!$D:$D,C6,合约状态!$V:$V) -> 0 | D27: =SUMIF(合约状态!$D:$D,D6,合约状态!$V:$V)*1/242 -> 0 | E27: =SUMIF(合约状态!$D:$D,E6,合约状态!$V:$V) / 242 -> 111970.3 | G27: =SUM(B27:E27) -> 111970.3
A29: 已实现收益 | B29: =SUMIF(了结合约!$D:$D,B6,了结合约!$AB:$AB) -> 0 | C29: =SUMIF(了结合约!$D:$D,C6,了结合约!$AB:$AB) -> 0 | D29: =SUMIF(了结合约!$D:$D,D6,了结合约!$AB:$AB) -> 2881016.4 | E29: =SUMIF(了结合约!$D:$D,E6,了结合约!$AB:$AB) -> 5796812.6 | G29: =SUM(B29:E29) -> 8677829
A30: 累积收益 | B30: =B12+B29 -> 0 | C30: =C12+C29 -> 0 | D30: =D12+D29 -> 2881016.4 | E30: =E12+E29 -> 8050387.4 | G30: =G12+G29 -> 10931404
A33: 累积估值 | G33: 合计
A34: 昨日估值 | B34: =SUMIF(合约状态!$D:$D,B30,合约状态!$AM:$AM) -> 0 | C34: =SUMIF(合约状态!$D:$D,C30,合约状态!$AM:$AM) -> 0 | D34: =SUMIF(合约状态!$D:$D,D6,合约状态!$AM:$AM) + SUMIF(了结合约!$D:$D,D6,了结合约!$R:$R) -> 2881016.4 | E34: =SUMIF(合约状态!$D:$D,E6,合约状态!$AM:$AM)+ SUMIF(合约状态!$D:$D,E6,合约状态!$AB:$AB) + SUMIF(了结合约!$D:$D,E6,了结合约!$R:$R) -> 5310059 | G34: =SUM(B34:E34) -> 8191075.4
A35: 当日估值 | B35: =SUMIF(合约状态!$D:$D,B30,合约状态!$R:$R) -> 0 | C35: =SUMIF(合约状态!$D:$D,C30,合约状态!$R:$R) -> 0 | D35: =SUMIF(合约状态!$D:$D,D6,合约状态!$R:$R) + SUMIF(了结合约!$D:$D,D6,了结合约!$R:$R) -> 2881016.4 | E35: =SUMIF(合约状态!$D:$D,E6,合约状态!$R:$R)+ SUMIF(合约状态!$D:$D,E30,合约状态!$AB:$AB) + SUMIF(了结合约!$D:$D,E6,了结合约!$R:$R) -> 6514613.5 | G35: =SUM(B35:E35) -> 9395630

Sheet 了结合约
A1: 合约类型 | B1: 合约编号 | C1: 名义本金 | D1: 挂钩标的 | E1: 起始日期 | F1: 期初价格 | G1: 敲入点位 | H1: 敲入距离 | I1: 距离敲出线 | J1: 下一敲出观察 | K1: 下一敲出票息率 | L1: 下次敲出票息 | M1: 次级票息 | N1: 距离合约结束 | O1: TERMINATION DATE | P1: DATE | Q1: SPOT | R1: NPV | S1: DELTA | T1: GAMMA | U1: VEGA | V1: THETA | W1: RHO | X1: RHO Q | Y1: RISK FREE RATE | Z1: CARRY COST | AA1: VOLATILITY | AB1: 已了结收益 | AC1: 期初价格 | AD1: 起息日 | AE1: 敲入障碍价格 | AF1: 每日观察敲入 | AG1: 敲入执行价格 | AH1: 敲入参与率 | AI1: 是否已敲入 | AJ1: 红利票息 | AK1: 保证金比例 | AL1: 最大亏损比例 | AM1: 昨日NPV | AP1: 敲出观察 | AR1: 敲出障碍 | AT1: 派息观察日 | AV1: 派息月息
A2: SNB | B2: 12 | C2: 22000000 | D2: 000852.SH | E2: 46021.625 | F2: 7597.3 | O2: 2026.3.30 | Y2: 0.021 | Z2: -0.07741 | AA2: 0.175 | AB2: 1535780.8 | AC2: 7597.3 | AD2: 46021.625 | AE2: 0.65 | AF2: TRUE | AG2: 1 | AH2: 1 | AI2: FALSE | AJ2: 0.05 | AK2: 1 | AL2: 1 | AM2: {=TRANSPOSE(_xll.ValuateSnowball(实时行情!$D$1,F2,AD2,AN2:BI2,BJ2:CE2,CF2:DA2,0,AJ2,AE2,AG2,AH2,AK2,AL2,0,0,0,TRUE,AF2,实时行情!$B$2,实时行情!$E$8,Y2,Z2,AA2,FALSE,"NPV")*C2/F2)} -> 1794048.4 | AN2: 46111 | AO2: 46142 | AP2: 46171 | AQ2: 46203 | AR2: 46233 | AS2: 46265 | AT2: 46295 | AU2: 46325 | AV2: 46356 | AW2: 46386 | AX2: 46416 | AY2: 46444 | AZ2: 46476 | BA2: 46507 | BB2: 46538 | BC2: 46568 | BD2: 46598 | BE2: 46629 | BF2: 46660 | BG2: 46689 | BH2: 46721 | BI2: 46751 | BJ2: 1 | BK2: 1 | BL2: 1 | BM2: 1 | BN2: 1 | BO2: 1 | BP2: 1 | BQ2: 1 | BR2: 1 | BS2: 1 | BT2: 1 | BU2: 1 | BV2: 1 | BW2: 1 | BX2: 1 | BY2: 1 | BZ2: 1 | CA2: 1 | CB2: 1 | CC2: 1 | CD2: 1 | CE2: 1 | CF2: 0.28 | CG2: 0.28 | CH2: 0.28 | CI2: 0.28 | CJ2: 0.28 | CK2: 0.28 | CL2: 0.28 | CM2: 0.28 | CN2: 0.28 | CO2: 0.28 | CP2: 0.05 | CQ2: 0.05 | CR2: 0.05 | CS2: 0.05 | CT2: 0.05 | CU2: 0.05 | CV2: 0.05 | CW2: 0.05 | CX2: 0.05 | CY2: 0.05 | CZ2: 0.05 | DA2: 0.05
A3: SNB | B3: 11 | C3: 10000000 | D3: 000852.SH | F3: 7579.38 | O3: 2026.2.25 | R3: 552328.77 | Y3: 0.021 | Z3: -0.07571 | AA3: 0.175 | AB3: 552328.77 | AC3: 7579.38 | AD3: 46016.625 | AE3: 0.7 | AF3: TRUE | AG3: 1 | AH3: 1 | AI3: FALSE | AJ3: 0.1 | AK3: 1 | AL3: 1 | AM3: {=TRANSPOSE(_xll.ValuateSnowball(实时行情!$D$1,AC3,AD3,AN3:BJ3,BK3:CG3,CH3:DD3,0,AJ3,AE3,AG3,AH3,AK3,AL3,0,0,0,TRUE,AF3,实时行情!$B$2,实时行情!E8,Y3,Z3,AA3,FALSE,"NPV")*C3/AC3)} -> 993498.22 | AN3: 46078 | AO3: 46106 | AP3: 46139 | AQ3: 46167 | AR3: 46198 | AS3: 46230 | AT3: 46259 | AU3: 46293 | AV3: 46321 | AW3: 46351 | AX3: 46381 | AY3: 46412 | AZ3: 46443 | BA3: 46471 | BB3: 46503 | BC3: 46532 | BD3: 46563 | BE3: 46594 | BF3: 46624 | BG3: 46657 | BH3: 46685 | BI3: 46716 | BJ3: 46748 | BK3: 1 | BL3: 1 | BM3: 1 | BN3: 1 | BO3: 1 | BP3: 1 | BQ3: 1 | BR3: 1 | BS3: 1 | BT3: 1 | BU3: 1 | BV3: 1 | BW3: 1 | BX3: 1 | BY3: 1 | BZ3: 1 | CA3: 1 | CB3: 1 | CC3: 1 | CD3: 1 | CE3: 1 | CF3: 1 | CG3: 1 | CH3: 0.32 | CI3: 0.32 | CJ3: 0.32 | CK3: 0.32 | CL3: 0.32 | CM3: 0.32 | CN3: 0.32 | CO3: 0.32 | CP3: 0.32 | CQ3: 0.32 | CR3: 0.32 | CS3: 0.1 | CT3: 0.1 | CU3: 0.1 | CV3: 0.1 | CW3: 0.1 | CX3: 0.1 | CY3: 0.1 | CZ3: 0.1 | DA3: 0.1 | DB3: 0.1 | DC3: 0.1 | DD3: 0.1
A4: SNB | B4: 10 | C4: 10000000 | D4: 000905.SH | F4: 7235.46 | O4: 2026.2.24 | R4: 997830.14 | Y4: 0.021 | Z4: -0.06504 | AA4: 0.16 | AB4: 997830.14 | AC4: 7235.46 | AD4: 45975.625 | AE4: 0.75 | AF4: TRUE | AG4: 1 | AH4: 1 | AI4: FALSE | AJ4: 0.05 | AK4: 1 | AL4: 1 | AM4: {=TRANSPOSE(_xll.ValuateSnowball(实时行情!D1,AC4,AD4,AN4:BI4,BJ4:CE4,CF4:DA4,0,AJ4,AE4,AG4,AH4,AK4,AL4,0,0,0,TRUE,AF4,实时行情!B2,实时行情!D8,Y4,Z4,AA4,FALSE,"NPV")*C4/AC4)} -> 1469532.8 | AN4: 46077 | AO4: 46097 | AP4: 46126 | AQ4: 46156 | AR4: 46188 | AS4: 46217 | AT4: 46248 | AU4: 46279 | AV4: 46309 | AW4: 46342 | AX4: 46370 | AY4: 46401 | AZ4: 46433 | BA4: 46461 | BB4: 46491 | BC4: 46521 | BD4: 46552 | BE4: 46582 | BF4: 46615 | BG4: 46644 | BH4: 46674 | BI4: 46706 | BJ4: 1 | BK4: 1 | BL4: 1 | BM4: 1 | BN4: 1 | BO4: 1 | BP4: 1 | BQ4: 1 | BR4: 1 | BS4: 1 | BT4: 1 | BU4: 1 | BV4: 1 | BW4: 1 | BX4: 1 | BY4: 1 | BZ4: 1 | CA4: 1 | CB4: 1 | CC4: 1 | CD4: 1 | CE4: 1 | CF4: 0.3536 | CG4: 0.3536 | CH4: 0.3536 | CI4: 0.3536 | CJ4: 0.3536 | CK4: 0.3536 | CL4: 0.3536 | CM4: 0.3536 | CN4: 0.3536 | CO4: 0.3536 | CP4: 0.05 | CQ4: 0.05 | CR4: 0.05 | CS4: 0.05 | CT4: 0.05 | CU4: 0.05 | CV4: 0.05 | CW4: 0.05 | CX4: 0.05 | CY4: 0.05 | CZ4: 0.05 | DA4: 0.05
A5: SNB | B5: 9 | C5: 10000000 | D5: 000905.SH | F5: 7248.9 | O5: 2026.2.3 | R5: 924904.11 | Y5: 0.021 | Z5: -0.06087 | AA5: 0.165 | AB5: 924904.11 | AC5: 7248.9 | AD5: 45964.625 | AE5: 0.75 | AF5: TRUE | AG5: 1 | AH5: 1 | AI5: FALSE | AJ5: 0.05 | AK5: 1 | AL5: 1 | AM5: {=TRANSPOSE(_xll.ValuateSnowball(实时行情!$D$1,AC5,AD5,AN5:BI5,BJ5:CE5,CF5:DA5,0,AJ5,AE5,AG5,AH5,AK5,AL5,0,0,0,TRUE,AF5,实时行情!B2,实时行情!D8,Y5,Z5,AA5,FALSE,"NPV")*C5/AC5)} -> 1796846.7 | AN5: 46056 | AO5: 46084 | AP5: 46115 | AQ5: 46148 | AR5: 46176 | AS5: 46206 | AT5: 46237 | AU5: 46268 | AV5: 46303 | AW5: 46329 | AX5: 46359 | AY5: 46391 | AZ5: 46421 | BA5: 46449 | BB5: 46483 | BC5: 46513 | BD5: 46541 | BE5: 46573 | BF5: 46602 | BG5: 46633 | BH5: 46668 | BI5: 46694 | BJ5: 1 | BK5: 1 | BL5: 1 | BM5: 1 | BN5: 1 | BO5: 1 | BP5: 1 | BQ5: 1 | BR5: 1 | BS5: 1 | BT5: 1 | BU5: 1 | BV5: 1 | BW5: 1 | BX5: 1 | BY5: 1 | BZ5: 1 | CA5: 1 | CB5: 1 | CC5: 1 | CD5: 1 | CE5: 1 | CF5: 0.363 | CG5: 0.363 | CH5: 0.363 | CI5: 0.363 | CJ5: 0.363 | CK5: 0.363 | CL5: 0.363 | CM5: 0.363 | CN5: 0.363 | CO5: 0.363 | CP5: 0.05 | CQ5: 0.05 | CR5: 0.05 | CS5: 0.05 | CT5: 0.05 | CU5: 0.05 | CV5: 0.05 | CW5: 0.05 | CX5: 0.05 | CY5: 0.05 | CZ5: 0.05 | DA5: 0.05
A6: SNB | B6: 8 | C6: 10000000 | D6: 000852.SH | F6: 7550.41 | O6: 2026.1.30 | R6: 930000 | Y6: 0.021 | Z6: -0.08497 | AA6: 0.18 | AB6: 930000 | AC6: 7550.41 | AD6: 45960.625 | AE6: 0.7 | AF6: TRUE | AG6: 1 | AH6: 1 | AI6: FALSE | AJ6: 0.05 | AK6: 1 | AL6: 1 | AM6: {=TRANSPOSE(_xll.ValuateSnowball(实时行情!$D$1,AC6,AD6,AN6:BI6,BJ6:CE6,CF6:DA6,0,AJ6,AE6,AG6,AH6,AK6,AL6,0,0,0,TRUE,AF6,实时行情!$B$2,实时行情!E8,Y6,Z6,AA6,FALSE,"NPV")*C6/AC6)} -> 1722783.8 | AN6: 46052 | AO6: 46080 | AP6: 46111 | AQ6: 46142 | AR6: 46171 | AS6: 46203 | AT6: 46233 | AU6: 46265 | AV6: 46295 | AW6: 46325 | AX6: 46356 | AY6: 46386 | AZ6: 46416 | BA6: 46444 | BB6: 46476 | BC6: 46507 | BD6: 46538 | BE6: 46568 | BF6: 46598 | BG6: 46629 | BH6: 46660 | BI6: 46689 | BJ6: 1 | BK6: 0.995 | BL6: 0.99 | BM6: 0.985 | BN6: 0.98 | BO6: 0.975 | BP6: 0.97 | BQ6: 0.965 | BR6: 0.96 | BS6: 0.955 | BT6: 0.95 | BU6: 0.945 | BV6: 0.94 | BW6: 0.935 | BX6: 0.93 | BY6: 0.925 | BZ6: 0.92 | CA6: 0.915 | CB6: 0.91 | CC6: 0.905 | CD6: 0.9 | CE6: 0.895 | CF6: 0.365 | CG6: 0.365 | CH6: 0.365 | CI6: 0.365 | CJ6: 0.365 | CK6: 0.365 | CL6: 0.365 | CM6: 0.365 | CN6: 0.365 | CO6: 0.365 | CP6: 0.05 | CQ6: 0.05 | CR6: 0.05 | CS6: 0.05 | CT6: 0.05 | CU6: 0.05 | CV6: 0.05 | CW6: 0.05 | CX6: 0.05 | CY6: 0.05 | CZ6: 0.05 | DA6: 0.05
A7: SNB | B7: 7 | C7: 10000000 | D7: 000852.SH | F7: 7209.61 | O7: 2026.1.23 | R7: 751134.25 | Y7: 0.021 | Z7: -0.0725 | AA7: 0.17 | AB7: 751134.25 | AC7: 7209.61 | AD7: 45953.625 | AE7: 0.7 | AF7: TRUE | AG7: 1 | AH7: 1 | AI7: FALSE | AJ7: 0.05 | AK7: 1 | AL7: 1 | AM7: {=TRANSPOSE(_xll.ValuateSnowball(实时行情!$D$1,AC7,AD7,AN7:BI7,BJ7:CE7,CF7:DA7,0,AJ7,AE7,AG7,AH7,AK7,AL7,0,0,0,TRUE,AF7,实时行情!$B$2,实时行情!E8,Y7,Z7,AA7,FALSE,"NPV")*C7/AC7)} -> 1467502.8 | AN7: 46045 | AO7: 46077 | AP7: 46104 | AQ7: 46135 | AR7: 46167 | AS7: 46196 | AT7: 46226 | AU7: 46258 | AV7: 46288 | AW7: 46318 | AX7: 46349 | AY7: 46379 | AZ7: 46412 | BA7: 46441 | BB7: 46469 | BC7: 46500 | BD7: 46531 | BE7: 46561 | BF7: 46591 | BG7: 46622 | BH7: 46653 | BI7: 46685 | BJ7: 1 | BK7: 0.995 | BL7: 0.99 | BM7: 0.985 | BN7: 0.98 | BO7: 0.975 | BP7: 0.97 | BQ7: 0.965 | BR7: 0.96 | BS7: 0.955 | BT7: 0.95 | BU7: 0.945 | BV7: 0.94 | BW7: 0.935 | BX7: 0.93 | BY7: 0.925 | BZ7: 0.92 | CA7: 0.915 | CB7: 0.91 | CC7: 0.905 | CD7: 0.9 | CE7: 0.895 | CF7: 0.2948 | CG7: 0.2948 | CH7: 0.2948 | CI7: 0.2948 | CJ7: 0.2948 | CK7: 0.2948 | CL7: 0.2948 | CM7: 0.2948 | CN7: 0.2948 | CO7: 0.2948 | CP7: 0.05 | CQ7: 0.05 | CR7: 0.05 | CS7: 0.05 | CT7: 0.05 | CU7: 0.05 | CV7: 0.05 | CW7: 0.05 | CX7: 0.05 | CY7: 0.05 | CZ7: 0.05 | DA7: 0.05
A8: SNB | B8: 6 | C8: 10000000 | D8: 000852.SH | F8: 7408.07 | O8: 2026.1.23 | R8: 1018709.6 | Y8: 0.021 | Z8: -0.077 | AA8: 0.17 | AB8: 1018709.6 | AC8: 7408.07 | AD8: 45923.625 | AE8: 0.7 | AF8: TRUE | AG8: 1 | AH8: 1 | AI8: FALSE | AJ8: 0.05 | AK8: 1 | AL8: 1 | AM8: {=TRANSPOSE(_xll.ValuateSnowball(实时行情!$D$1,AC8,AD8,AN8:BI8,BJ8:CE8,CF8:DA8,0,AJ8,AE8,AG8,AH8,AK8,AL8,0,0,0,TRUE,AF8,实时行情!$B$2,实时行情!E8,Y8,Z8,AA8,FALSE,"NPV")*C8/AC8)} -> 1748422.9 | AN8: 46014 | AO8: 46045 | AP8: 46077 | AQ8: 46104 | AR8: 46135 | AS8: 46167 | AT8: 46196 | AU8: 46226 | AV8: 46258 | AW8: 46288 | AX8: 46318 | AY8: 46349 | AZ8: 46379 | BA8: 46412 | BB8: 46441 | BC8: 46469 | BD8: 46500 | BE8: 46531 | BF8: 46561 | BG8: 46591 | BH8: 46622 | BI8: 46653 | BJ8: 1 | BK8: 0.995 | BL8: 0.99 | BM8: 0.985 | BN8: 0.98 | BO8: 0.975 | BP8: 0.97 | BQ8: 0.965 | BR8: 0.96 | BS8: 0.955 | BT8: 0.95 | BU8: 0.945 | BV8: 0.94 | BW8: 0.935 | BX8: 0.93 | BY8: 0.925 | BZ8: 0.92 | CA8: 0.915 | CB8: 0.91 | CC8: 0.905 | CD8: 0.9 | CE8: 0.895 | CF8: 0.3023 | CG8: 0.3023 | CH8: 0.3023 | CI8: 0.3023 | CJ8: 0.3023 | CK8: 0.3023 | CL8: 0.3023 | CM8: 0.3023 | CN8: 0.3023 | CO8: 0.3023 | CP8: 0.05 | CQ8: 0.05 | CR8: 0.05 | CS8: 0.05 | CT8: 0.05 | CU8: 0.05 | CV8: 0.05 | CW8: 0.05 | CX8: 0.05 | CY8: 0.05 | CZ8: 0.05 | DA8: 0.05
A9: PHX | B9: 5 | C9: 10000000 | D9: 000852.SH | F9: 7253.81 | L9: =C9*K9 -> 0 | O9: 2025.12.22 | R9: =86160*4 -> 344640 | Y9: 0.021 | Z9: -0.048 | AA9: 0.14 | AB9: =86160*4 -> 344640 | AC9: 7253.81 | AD9: 45890 | AE9: 0.75 | AF9: TRUE | AG9: 1 | AH9: 1 | AI9: FALSE | AJ9: 0 | AK9: 1 | AL9: 1 | AM9: {=TRANSPOSE(_xll.ValuatePhoenix(实时行情!D1,"UP_OUT",AC9,AD9,CF9:DC9,DD9:EA9,AN9:BI9,BJ9:CE9,EB9,AE9,AF9,AG9,AH9,AL9,AK9,0,0,实时行情!B2,实时行情!E8,Y9,Z9,AA9,FALSE,"NPV")*C9/AC9)} -> 78994.134 | AN9: 45982 | AO9: 46013 | AP9: 46043 | AQ9: 46077 | AR9: 46104 | AS9: 46133 | AT9: 46163 | AU9: 46195 | AV9: 46224 | AW9: 46255 | AX9: 46286 | AY9: 46316 | AZ9: 46349 | BA9: 46377 | BB9: 46408 | BC9: 46440 | BD9: 46468 | BE9: 46498 | BF9: 46528 | BG9: 46559 | BH9: 46589 | BI9: 46622 | BJ9: 1 | BK9: 0.995 | BL9: 0.99 | BM9: 0.985 | BN9: 0.98 | BO9: 0.975 | BP9: 0.97 | BQ9: 0.965 | BR9: 0.96 | BS9: 0.955 | BT9: 0.95 | BU9: 0.945 | BV9: 0.94 | BW9: 0.935 | BX9: 0.93 | BY9: 0.925 | BZ9: 0.92 | CA9: 0.915 | CB9: 0.91 | CC9: 0.905 | CD9: 0.9 | CE9: 0.895 | CF9: 45922 | CG9: 45951 | CH9: 45982 | CI9: 46013 | CJ9: 46043 | CK9: 46077 | CL9: 46104 | CM9: 46133 | CN9: 46163 | CO9: 46195 | CP9: 46224 | CQ9: 46255 | CR9: 46286 | CS9: 46316 | CT9: 46349 | CU9: 46377 | CV9: 46408 | CW9: 46440 | CX9: 46468 | CY9: 46498 | CZ9: 46528 | DA9: 46559 | DB9: 46589 | DC9: 46622 | DD9: 0.0086 | DE9: 0.0086 | DF9: 0.0086 | DG9: 0.0086 | DH9: 0.0086 | DI9: 0.0086 | DJ9: 0.0086 | DK9: 0.0086 | DL9: 0.0086 | DM9: 0.0086 | DN9: 0.0086 | DO9: 0.0086 | DP9: 0.0086 | DQ9: 0.0086 | DR9: 0.0086 | DS9: 0.0086 | DT9: 0.0086 | DU9: 0.0086 | DV9: 0.0086 | DW9: 0.0086 | DX9: 0.0086 | DY9: 0.0086 | DZ9: 0.0086 | EA9: 0.0086 | EB9: 0.8
A10: SNB | B10: 4 | C10: 10000000 | D10: 000905.SH | F10: 6357.38 | O10: 2025.11.6 | R10: 479268.49 | AB10: 479268.49 | AC10: 6357.38 | AD10: 45875
A11: SNB | B11: 3 | C11: 10000000 | D11: 000905.SH | F11: 6312.47 | O11: 2025.10.29 | R11: 479013.7 | AB11: 479013.7 | AC11: 6312.47 | AD11: 45867
A12: SNB | B12: 2 | C12: 10000000 | D12: 000852.SH | F12: 6706.61 | O12: 2025.10.27 | R12: 329767.12 | AB12: 329767.12 | AC12: 6706.61 | AD12: 45863
A13: SNB | B13: 1 | C13: 10000000 | D13: 000852.SH | F13: 6535.26 | O13: 2025.10.20 | R13: 334458.97 | AB13: 334452.05 | AC13: 6535.26 | AD13: 45856
Z18: 25年 合计 | AA18: =SUM(AB9:AB13) -> 1967141.4
Z19: 26年合计 | AA19: =SUM(AB2:AB8) -> 6710687.7
Z20: 合计 | AA20: =SUM(AB2:AB25) -> 8677829

Sheet Sheet2
A1: 存量合约估值情景分析
B2: 悲观（7000） | C2: 横盘（8000） | D2: 乐观（9000）
A3: 当前（7746） | B3: =SUMIF(合约状态!$D:$D,#REF!,合约状态!$R:$R)+ SUMIF(合约状态!$D:$D,#REF!,合约状态!$AB:$AB) -> 0 | C3: =SUMIF(合约状态!$D:$D,#REF!,合约状态!$R:$R)+ SUMIF(合约状态!$D:$D,#REF!,合约状态!$AB:$AB) -> 0 | D3: =SUMIF(合约状态!$D:$D,#REF!,合约状态!$R:$R)+ SUMIF(合约状态!$D:$D,#REF!,合约状态!$AB:$AB) -> 0
A4: 46197.577 | B4: -11627699 | C4: 9058326.8 | D4: 14239220
A5: 46287.59 | B5: -6821684.2 | C5: 16649720 | D5: 22425426
A6: 46377.589 | B6: -2941050.2 | C6: 21166500 | D6: 30406782
A7: 46470.59 | B7: 3753951.8 | C7: 12290587 | D7: 12376086
