Workbook

Sheet 合约状态
A1: 合约编号 | B1: 合约类型 | C1: 名义本金 | D1: 挂钩标的 | E1: 起息日期 | F1: 期初价格 | G1: 敲入点位 | H1: 临近敲出观察日 | I1: 敲出票息率 | J1: 敲出票息 | K1: 次年票息 | L1: 敲入距离 | M1: 敲出距离 | N1: 下一敲出观察 | O1: 距离合约结束 | P1: 敲出观察比例 | Q1: 了结日期 | R1: DATE | S1: SPOT | T1: NPV | U1: DELTA | V1: GAMMA | W1: VEGA | X1: THETA | Y1: RHO | Z1: RHO Q | AA1: RISK FREE RATE | AB1: CARRY COST | AC1: VOLATILITY | AD1: 已了结收益 | AE1: 期初价格 | AF1: 起息日 | AG1: 敲入障碍价格 | AH1: 派息障碍价格 | AI1: 每日观察敲入 | AJ1: 敲入执行价格 | AK1: 敲入参与率 | AL1: 是否已敲入 | AM1: 红利票息 | AN1: 保证金比例 | AO1: 最大亏损比例 | AP1: 昨日NPV | AQ1: 敲出观察日 | AS1: 敲出障碍 | AT1: 敲出票息 | AU1: 派息观察日 | AW1: 派息月息
A2: 26 | B2: 早利雪球 | C2: 1800000 | D2: 000852.SH | E2: 46170.625 | F2: 8637.74 | G2: =F2*AG2 -> 5614.531 | H2: =N2 -> 46262 | I2: {=INDEX(CI:DD,ROW(), MATCH(H2, AQ2:BL2, 0))} -> 0.22 | J2: =(N2-AF2)/365*C2*I2 -> 99135.616 | K2: 0.07 | L2: =实时行情!$E$7 /( 合约状态!F4 *合约状态!AG4)-1 -> 0.47727774 | M2: {=TRANSPOSE(_xll.DistanceToNearestBarrier(R2,S2,F2,AQ2:BL2,BM2:CH2))} -> 0.021053992 | N2: 46262 | O2: =BL2-R2 -> 724.53624 | P2: {=INDEX(BM:CH,ROW(), MATCH(H2, AQ2:BL2, 0))} -> 1 | R2: =实时行情!$A$2 -> 46178.464 | S2: =实时行情!E7 -> 8459.631 | T2: {=TRANSPOSE(_xll.ValuateSnowball(实时行情!$D$1,F2,E2,AQ2:BL2,BM2:CH2,CI2:DD2,0,AM2,AG2,AJ2,AK2,AN2,AO2,0,0,0,TRUE,AI2,R2,S2,AA2,AB2,AC2,AL2,"ALL")*C2/F2)} -> -18785.359 | U2: 152.83864 | V2: -0.14131211 | W2: -1307590.1 | X2: 291716.63 | Y2: -1502955.8 | Z2: -1618426.8 | AA2: 0.021 | AB2: -0.0695 | AC2: 0.18 | AD2: 0 | AE2: 8637.74 | AF2: 46170.625 | AG2: 0.65 | AI2: TRUE | AJ2: 1 | AK2: 1 | AL2: FALSE | AM2: 0.07 | AN2: 1 | AO2: 1 | AP2: {=IF(ISERROR(TRANSPOSE(_xll.ValuateSnowball(实时行情!$D$1,F2,AF2,AQ2:BL2,BM2:CH2,CI2:DD2,0,AM2,AG2,AJ2,AK2,AN2,AO2,0,0,0,TRUE,AI2,实时行情!$B$2,实时行情!E8,AA2,AB2,AC2,FALSE,"NPV")*C2/F2)), 0, TRANSPOSE(_xll.ValuateSnowball(实时行情!$D$1,F2,AF2,AQ2:BL2,BM2:CH2,CI2:DD2,0,AM2,AG2,AJ2,AK2,AN2,AO2,0,0,0,TRUE,AI2,实时行情!$B$2,实时行情!$E$8,AA2,AB2,AC2,FALSE,"NPV")*C2/F2))} -> -25583.309 | AQ2: 46262 | AR2: 46293 | AS2: 46323 | AT2: 46356 | AU2: 46384 | AV2: 46415 | AW2: 46444 | AX2: 46475 | AY2: 46505 | AZ2: 46535 | BA2: 46566 | BB2: 46596 | BC2: 46629 | BD2: 46658 | BE2: 46688 | BF2: 46720 | BG2: 46749 | BH2: 46776 | BI2: 46811 | BJ2: 46840 | BK2: 46871 | BL2: 46903 | BM2: 1 | BN2: 0.995 | BO2: 0.99 | BP2: 0.985 | BQ2: 0.98 | BR2: 0.975 | BS2: 0.97 | BT2: 0.965 | BU2: 0.96 | BV2: 0.955 | BW2: 0.95 | BX2: 0.945 | BY2: 0.94 | BZ2: 0.935 | CA2: 0.93 | CB2: 0.925 | CC2: 0.92 | CD2: 0.915 | CE2: 0.91 | CF2: 0.905 | CG2: 0.9 | CH2: 0.895 | CI2: 0.22 | CJ2: 0.22 | CK2: 0.22 | CL2: 0.22 | CM2: 0.22 | CN2: 0.22 | CO2: 0.22 | CP2: 0.22 | CQ2: 0.22 | CR2: 0.22 | CS2: 0.07 | CT2: 0.07 | CU2: 0.07 | CV2: 0.07 | CW2: 0.07 | CX2: 0.07 | CY2: 0.07 | CZ2: 0.07 | DA2: 0.07 | DB2: 0.07 | DC2: 0.07 | DD2: 0.07
A3: 25 | B3: DCN | C3: =18000000*0.89 -> 16020000 | D3: 000852.SH | E3: 46170.625 | F3: 8637.74 | G3: =F3*AG3 -> 5614.531 | H3: =N3 -> 46262 | L3: =实时行情!$E$7 /( 合约状态!F5 *合约状态!AG5)-1 -> 0.37019486 | M3: {=TRANSPOSE(_xll.DistanceToNearestBarrier(R3,S3,F3,AQ3:BL3,BM3:CH3))} -> 0.021053992 | N3: 46262 | O3: =BL3-R3 -> 724.53624 | P3: {=INDEX(BM:CH,ROW(), MATCH(H3, AQ3:BL3, 0))} -> 1 | R3: =实时行情!$A$2 -> 46178.464 | S3: =实时行情!E7 -> 8459.631 | T3: {=TRANSPOSE(_xll.ValuatePhoenix(实时行情!$D$1,"UP_OUT",F3,E3,CI3:DF3,DG3:ED3,AQ3:BL3,BM3:CH3,AH3,AG3,AI3,AJ3,AK3,AO3,AN3,0,0,R3,S3,AA3,AB3,AC3,AL3,"ALL"))*C3/F3} -> -55207.122 | U3: 536.00571 | V3: -0.79608575 | W3: -10021065 | X3: 1413724.8 | Y3: -13349045 | Z3: -8302117.8 | AA3: 0.021 | AB3: -0.058 | AC3: 0.17 | AD3: 0 | AE3: 8637.74 | AF3: 46170.625 | AG3: 0.65 | AH3: 0.75 | AI3: FALSE | AJ3: 1 | AK3: 1 | AL3: FALSE | AN3: 1 | AO3: 1 | AP3: {=IF(ISERROR(TRANSPOSE(_xll.ValuatePhoenix(实时行情!$D$1,"UP_OUT",F3,E3,CI3:DF3,DG3:ED3,AQ3:BL3,BM3:CH3,AH3,AG3,AI3,AJ3,AK3,AO3,AN3,0,0,实时行情!B2,实时行情!E8,AA3,AB3,AC3,AL3,"NPV")*C3/F3)), 0, TRANSPOSE(_xll.ValuatePhoenix(实时行情!$D$1,"UP_OUT",F3,E3,CI3:DF3,DG3:ED3,AQ3:BL3,BM3:CH3,AH3,AG3,AI3,AJ3,AK3,AO3,AN3,0,0,实时行情!B2,实时行情!E8,AA3,AB3,AC3,AL3,"NPV")*C3/F3))} -> -80232.048 | AQ3: 46262 | AR3: 46293 | AS3: 46323 | AT3: 46356 | AU3: 46384 | AV3: 46415 | AW3: 46444 | AX3: 46475 | AY3: 46505 | AZ3: 46535 | BA3: 46566 | BB3: 46596 | BC3: 46629 | BD3: 46658 | BE3: 46688 | BF3: 46720 | BG3: 46749 | BH3: 46776 | BI3: 46811 | BJ3: 46840 | BK3: 46871 | BL3: 46903 | BM3: 1 | BN3: 0.995 | BO3: 0.99 | BP3: 0.985 | BQ3: 0.98 | BR3: 0.975 | BS3: 0.97 | BT3: 0.965 | BU3: 0.96 | BV3: 0.955 | BW3: 0.95 | BX3: 0.945 | BY3: 0.94 | BZ3: 0.935 | CA3: 0.93 | CB3: 0.925 | CC3: 0.92 | CD3: 0.915 | CE3: 0.91 | CF3: 0.905 | CG3: 0.9 | CH3: 0.895 | CI3: 46202 | CJ3: 46231 | CK3: 46262 | CL3: 46293 | CM3: 46323 | CN3: 46356 | CO3: 46384 | CP3: 46415 | CQ3: 46444 | CR3: 46475 | CS3: 46505 | CT3: 46535 | CU3: 46566 | CV3: 46596 | CW3: 46629 | CX3: 46658 | CY3: 46688 | CZ3: 46720 | DA3: 46749 | DB3: 46776 | DC3: 46811 | DD3: 46840 | DE3: 46871 | DF3: 46903 | DG3: 0.0065 | DH3: 0.0065 | DI3: 0.0065 | DJ3: 0.0065 | DK3: 0.0065 | DL3: 0.0065 | DM3: 0.0065 | DN3: 0.0065 | DO3: 0.0065 | DP3: 0.0065 | DQ3: 0.0065 | DR3: 0.0065 | DS3: 0.0065 | DT3: 0.0065 | DU3: 0.0065 | DV3: 0.0065 | DW3: 0.0065 | DX3: 0.0065 | DY3: 0.0065 | DZ3: 0.0065 | EA3: 0.0065 | EB3: 0.0065 | EC3: 0.0065 | ED3: 0.0065
A4: 24 | B4: 凤凰 | C4: 30000000 | D4: 000852.SH | E4: 46157.625 | F4: 8810 | G4: =F4*AG4 -> 5726.5 | H4: =N4 -> 46251 | L4: =实时行情!$E$7 /( 合约状态!F6 *合约状态!AG6)-1 -> 0.48771539 | M4: {=TRANSPOSE(_xll.DistanceToNearestBarrier(R4,S4,F4,AQ4:BL4,BM4:CH4))} -> 0.041416582 | N4: 46251 | O4: =BL4-R4 -> 709.53624 | P4: {=INDEX(BM:CH,ROW(), MATCH(H4, AQ4:BL4, 0))} -> 1 | R4: =实时行情!$A$2 -> 46178.464 | S4: =实时行情!E7 -> 8459.631 | T4: {=TRANSPOSE(_xll.ValuatePhoenix(实时行情!$D$1,"UP_OUT",F4,E4,CI4:DF4,DG4:ED4,AQ4:BL4,BM4:CH4,AH4,AG4,AI4,AJ4,AK4,AO4,AN4,0,0,R4,S4,AA4,AB4,AC4,AL4,"ALL"))*C4/F4} -> -287689.73 | U4: 1811.4194 | V4: -2.2996474 | W4: -28890739 | X4: 4474268.6 | Y4: -29115950 | Z4: -25416993 | AA4: 0.021 | AB4: -0.0771 | AC4: 0.18 | AD4: 0 | AE4: 8490.62 | AF4: 46157.625 | AG4: 0.65 | AH4: 0.75 | AI4: TRUE | AJ4: 1 | AK4: 1 | AL4: FALSE | AN4: 1 | AO4: 1 | AP4: {=IF(ISERROR(TRANSPOSE(_xll.ValuatePhoenix(实时行情!$D$1,"UP_OUT",F4,E4,CI4:DF4,DG4:ED4,AQ4:BL4,BM4:CH4,AH4,AG4,AI4,AJ4,AK4,AO4,AN4,0,0,实时行情!B2,实时行情!E8,AA4,AB4,AC4,AL4,"NPV")*C4/F4)), 0, TRANSPOSE(_xll.ValuatePhoenix(实时行情!$D$1,"UP_OUT",F4,E4,CI4:DF4,DG4:ED4,AQ4:BL4,BM4:CH4,AH4,AG4,AI4,AJ4,AK4,AO4,AN4,0,0,实时行情!B2,实时行情!E8,AA4,AB4,AC4,AL4,"NPV")*C4/F4))} -> -371153.06 | AQ4: 46251 | AR4: 46280 | AS4: 46310 | AT4: 46342 | AU4: 46371 | AV4: 46402 | AW4: 46433 | AX4: 46461 | AY4: 46492 | AZ4: 46524 | BA4: 46553 | BB4: 46583 | BC4: 46615 | BD4: 46646 | BE4: 46675 | BF4: 46706 | BG4: 46736 | BH4: 46769 | BI4: 46798 | BJ4: 46827 | BK4: 46860 | BL4: 46888 | BM4: 1 | BN4: 1 | BO4: 1 | BP4: 1 | BQ4: 1 | BR4: 1 | BS4: 1 | BT4: 1 | BU4: 1 | BV4: 1 | BW4: 1 | BX4: 1 | BY4: 1 | BZ4: 1 | CA4: 1 | CB4: 1 | CC4: 1 | CD4: 1 | CE4: 1 | CF4: 1 | CG4: 1 | CH4: 1 | CI4: 46188 | CJ4: 46218 | CK4: 46251 | CL4: 46280 | CM4: 46310 | CN4: 46342 | CO4: 46371 | CP4: 46402 | CQ4: 46433 | CR4: 46461 | CS4: 46492 | CT4: 46524 | CU4: 46553 | CV4: 46583 | CW4: 46615 | CX4: 46646 | CY4: 46675 | CZ4: 46706 | DA4: 46736 | DB4: 46769 | DC4: 46798 | DD4: 46827 | DE4: 46860 | DF4: 46888 | DG4: 0.0099996482 | DH4: 0.0099996482 | DI4: 0.0099996482 | DJ4: 0.0099996482 | DK4: 0.0099996482 | DL4: 0.0099996482 | DM4: 0.0099996482 | DN4: 0.0099996482 | DO4: 0.0099996482 | DP4: 0.0099996482 | DQ4: 0.0099996482 | DR4: 0.0099996482 | DS4: 0.0099996482 | DT4: 0.0099996482 | DU4: 0.0099996482 | DV4: 0.0099996482 | DW4: 0.0099996482 | DX4: 0.0099996482 | DY4: 0.0099996482 | DZ4: 0.0099996482 | EA4: 0.0099996482 | EB4: 0.0099996482 | EC4: 0.0099996482 | ED4: 0.0099996482
A5: 23 | B5: 经典雪球 | C5: 14000000 | D5: 000852.SH | E5: 46157.625 | F5: 8820.05 | G5: =F5*AG5 -> 6174.035 | H5: =N5 -> 46251 | I5: {=INDEX(CI:DD,ROW(), MATCH(H5, AQ5:BL5, 0))} -> 0.15 | J5: =(N5-AF5)/365*C5*I5 -> 985993.15 | K5: 0.15 | L5: =实时行情!$E$7 /( 合约状态!F7 *合约状态!AG7)-1 -> 0.51784079 | M5: {=TRANSPOSE(_xll.DistanceToNearestBarrier(R5,S5,F5,AQ5:BL5,BM5:CH5))} -> 0.042604577 | N5: 46251 | O5: =BL5-R5 -> 709.53624 | P5: {=INDEX(BM:CH,ROW(), MATCH(H5, AQ5:BL5, 0))} -> 1 | R5: =实时行情!$A$2 -> 46178.464 | S5: =实时行情!E7 -> 8459.631 | T5: {=TRANSPOSE(_xll.ValuateSnowball(实时行情!$D$1,F5,AF5,AQ5:BL5,BM5:CH5,CI5:DD5,0,AM5,AG5,AJ5,AK5,AN5,AO5,0,0,0,TRUE,AI5,R5,S5,AA5,AB5,AC5,FALSE,"ALL")*C5/F5)} -> -311026.7 | U5: 1551.725 | V5: -1.1291951 | W5: -10853528 | X5: 2602881.9 | Y5: -12474039 | Z5: -16569121 | AA5: 0.021 | AB5: -0.0764 | AC5: 0.18 | AD5: 0 | AE5: 8490.62 | AF5: 46079.625 | AG5: 0.7 | AI5: TRUE | AJ5: 1 | AK5: 1 | AL5: FALSE | AM5: 0.1971 | AN5: 1 | AO5: 1 | AP5: {=IF(ISERROR(TRANSPOSE(_xll.ValuateSnowball(实时行情!$D$1,F5,AF5,AQ5:BL5,BM5:CH5,CI5:DD5,0,AM5,AG5,AJ5,AK5,AN5,AO5,0,0,0,TRUE,AI5,实时行情!$B$2,实时行情!E8,AA5,AB5,AC5,FALSE,"NPV")*C5/F5)), 0, TRANSPOSE(_xll.ValuateSnowball(实时行情!$D$1,F5,AF5,AQ5:BL5,BM5:CH5,CI5:DD5,0,AM5,AG5,AJ5,AK5,AN5,AO5,0,0,0,TRUE,AI5,实时行情!$B$2,实时行情!$E$8,AA5,AB5,AC5,FALSE,"NPV")*C5/F5))} -> -378976.23 | AQ5: 46251 | AR5: 46280 | AS5: 46310 | AT5: 46342 | AU5: 46371 | AV5: 46402 | AW5: 46433 | AX5: 46461 | AY5: 46492 | AZ5: 46524 | BA5: 46553 | BB5: 46583 | BC5: 46615 | BD5: 46646 | BE5: 46675 | BF5: 46706 | BG5: 46736 | BH5: 46769 | BI5: 46798 | BJ5: 46827 | BK5: 46860 | BL5: 46888 | BM5: 1 | BN5: 0.995 | BO5: 0.99 | BP5: 0.985 | BQ5: 0.98 | BR5: 0.975 | BS5: 0.97 | BT5: 0.965 | BU5: 0.96 | BV5: 0.955 | BW5: 0.95 | BX5: 0.945 | BY5: 0.94 | BZ5: 0.935 | CA5: 0.93 | CB5: 0.925 | CC5: 0.92 | CD5: 0.915 | CE5: 0.91 | CF5: 0.905 | CG5: 0.9 | CH5: 0.895 | CI5: 0.15 | CJ5: 0.15 | CK5: 0.15 | CL5: 0.15 | CM5: 0.15 | CN5: 0.15 | CO5: 0.15 | CP5: 0.15 | CQ5: 0.15 | CR5: 0.15 | CS5: 0.15 | CT5: 0.15 | CU5: 0.15 | CV5: 0.15 | CW5: 0.15 | CX5: 0.15 | CY5: 0.15 | CZ5: 0.15 | DA5: 0.15 | DB5: 0.15 | DC5: 0.15 | DD5: 0.15
A6: 22 | B6: 早利雪球 | C6: 11000000 | D6: 000852.SH | E6: 46150.625 | F6: 8748.19 | G6: =F6*AG6 -> 5686.3235 | H6: =N6 -> 46244 | I6: {=INDEX(CI:DD,ROW(), MATCH(H6, AQ6:BL6, 0))} -> 0.215 | J6: =(N6-AF6)/365*C6*I6 -> 605018.84 | K6: 0.05 | L6: =实时行情!$E$7 /( 合约状态!F8 *合约状态!AG8)-1 -> 0.44181093 | M6: {=TRANSPOSE(_xll.DistanceToNearestBarrier(R6,S6,F6,AQ6:BL6,BM6:CH6))} -> 0.034110117 | N6: 46244 | O6: =BL6-R6 -> 702.53624 | P6: {=INDEX(BM:CH,ROW(), MATCH(H6, AQ6:BL6, 0))} -> 1 | R6: =实时行情!$A$2 -> 46178.464 | S6: =实时行情!E7 -> 8459.631 | T6: {=TRANSPOSE(_xll.ValuateSnowball(实时行情!$D$1,F6,E6,AQ6:BL6,BM6:CH6,CI6:DD6,0,AM6,AG6,AJ6,AK6,AN6,AO6,0,0,0,TRUE,AI6,R6,S6,AA6,AB6,AC6,AL6,"ALL")*C6/F6)} -> -92308.364 | U6: 898.40084 | V6: -0.69880697 | W6: -6192265.8 | X6: 1627209.4 | Y6: -10557697 | Z6: -9781785 | AA6: 0.021 | AB6: -0.077 | AC6: 0.18 | AD6: 0 | AE6: 8748.19 | AF6: 46150.625 | AG6: 0.65 | AI6: FALSE | AJ6: 1 | AK6: 1 | AL6: FALSE | AM6: 0.05 | AN6: 1 | AO6: 1 | AP6: {=IF(ISERROR(TRANSPOSE(_xll.ValuateSnowball(实时行情!$D$1,F6,AF6,AQ6:BL6,BM6:CH6,CI6:DD6,0,AM6,AG6,AJ6,AK6,AN6,AO6,0,0,0,TRUE,AI6,实时行情!$B$2,实时行情!E8,AA6,AB6,AC6,FALSE,"NPV")*C6/F6)), 0, TRANSPOSE(_xll.ValuateSnowball(实时行情!$D$1,F6,AF6,AQ6:BL6,BM6:CH6,CI6:DD6,0,AM6,AG6,AJ6,AK6,AN6,AO6,0,0,0,TRUE,AI6,实时行情!$B$2,实时行情!$E$8,AA6,AB6,AC6,FALSE,"NPV")*C6/F6))} -> -131932.05 | AQ6: 46244 | AR6: 46273 | AS6: 46303 | AT6: 46335 | AU6: 46364 | AV6: 46395 | AW6: 46433 | AX6: 46454 | AY6: 46485 | AZ6: 46517 | BA6: 46546 | BB6: 46576 | BC6: 46608 | BD6: 46638 | BE6: 46668 | BF6: 46699 | BG6: 46729 | BH6: 46762 | BI6: 46791 | BJ6: 46820 | BK6: 46853 | BL6: 46881 | BM6: 1 | BN6: 1 | BO6: 1 | BP6: 1 | BQ6: 1 | BR6: 1 | BS6: 1 | BT6: 1 | BU6: 1 | BV6: 1 | BW6: 1 | BX6: 1 | BY6: 1 | BZ6: 1 | CA6: 1 | CB6: 1 | CC6: 1 | CD6: 1 | CE6: 1 | CF6: 1 | CG6: 1 | CH6: 1 | CI6: 0.215 | CJ6: 0.215 | CK6: 0.215 | CL6: 0.215 | CM6: 0.215 | CN6: 0.215 | CO6: 0.215 | CP6: 0.215 | CQ6: 0.215 | CR6: 0.215 | CS6: 0.05 | CT6: 0.05 | CU6: 0.05 | CV6: 0.05 | CW6: 0.05 | CX6: 0.05 | CY6: 0.05 | CZ6: 0.05 | DA6: 0.05 | DB6: 0.05 | DC6: 0.05 | DD6: 0.05
A7: 21 | B7: 早利雪球 | C7: 11000000 | D7: 000852.SH | E7: 46148.625 | F7: 8574.56 | G7: =F7*AG7 -> 5573.464 | H7: =N7 -> 46240 | I7: {=INDEX(CI:DD,ROW(), MATCH(H7, AQ7:BL7, 0))} -> 0.16 | J7: =(N7-AF7)/365*C7*I7 -> 440602.74 | K7: 0.1 | L7: =实时行情!$E$7 /( 合约状态!F9 *合约状态!AG9)-1 -> 0.44181093 | M7: {=TRANSPOSE(_xll.DistanceToNearestBarrier(R7,S7,F7,AQ7:BL7,BM7:CH7))} -> 0.013585581 | N7: 46240 | O7: =BL7-R7 -> 702.53624 | P7: {=INDEX(BM:CH,ROW(), MATCH(H7, AQ7:BL7, 0))} -> 1 | R7: =实时行情!$A$2 -> 46178.464 | S7: =实时行情!E7 -> 8459.631 | T7: {=TRANSPOSE(_xll.ValuateSnowball(实时行情!$D$1,F7,E7,AQ7:BL7,BM7:CH7,CI7:DD7,0,AM7,AG7,AJ7,AK7,AN7,AO7,0,0,0,TRUE,AI7,R7,S7,AA7,AB7,AC7,AL7,"ALL")*C7/F7)} -> 60794.804 | U7: 692.14188 | V7: -0.98911191 | W7: -11055578 | X7: 1628522.5 | Y7: -9950818.5 | Z7: -9262793.7 | AA7: 0.021 | AB7: -0.08275 | AC7: 0.16 | AD7: 0 | AE7: 8574.56 | AF7: 46148.625 | AG7: 0.65 | AI7: TRUE | AJ7: 1 | AK7: 1 | AL7: FALSE | AM7: 0.1 | AN7: 1 | AO7: 1 | AP7: {=IF(ISERROR(TRANSPOSE(_xll.ValuateSnowball(实时行情!$D$1,F7,AF7,AQ7:BL7,BM7:CH7,CI7:DD7,0,AM7,AG7,AJ7,AK7,AN7,AO7,0,0,0,TRUE,AI7,实时行情!$B$2,实时行情!E8,AA7,AB7,AC7,FALSE,"NPV")*C7/F7)), 0, TRANSPOSE(_xll.ValuateSnowball(实时行情!$D$1,F7,AF7,AQ7:BL7,BM7:CH7,CI7:DD7,0,AM7,AG7,AJ7,AK7,AN7,AO7,0,0,0,TRUE,AI7,实时行情!$B$2,实时行情!$E$8,AA7,AB7,AC7,FALSE,"NPV")*C7/F7))} -> 29003.021 | AQ7: 46240 | AR7: 46272 | AS7: 46303 | AT7: 46332 | AU7: 46363 | AV7: 46393 | AW7: 46433 | AX7: 46454 | AY7: 46483 | AZ7: 46513 | BA7: 46545 | BB7: 46574 | BC7: 46605 | BD7: 46636 | BE7: 46668 | BF7: 46699 | BG7: 46727 | BH7: 46758 | BI7: 46790 | BJ7: 46818 | BK7: 46849 | BL7: 46881 | BM7: 1 | BN7: 1 | BO7: 1 | BP7: 1 | BQ7: 1 | BR7: 1 | BS7: 1 | BT7: 1 | BU7: 1 | BV7: 1 | BW7: 1 | BX7: 1 | BY7: 1 | BZ7: 1 | CA7: 1 | CB7: 1 | CC7: 1 | CD7: 1 | CE7: 1 | CF7: 1 | CG7: 1 | CH7: 1 | CI7: 0.16 | CJ7: 0.16 | CK7: 0.16 | CL7: 0.16 | CM7: 0.16 | CN7: 0.16 | CO7: 0.16 | CP7: 0.16 | CQ7: 0.16 | CR7: 0.16 | CS7: 0.1 | CT7: 0.1 | CU7: 0.1 | CV7: 0.1 | CW7: 0.1 | CX7: 0.1 | CY7: 0.1 | CZ7: 0.1 | DA7: 0.1 | DB7: 0.1 | DC7: 0.1 | DD7: 0.1
A8: 28 | B8: 早利雪球 | C8: 5000000 | D8: 000852.SH | E8: 46142.625 | F8: 8381.95 | G8: =F8*AG8 -> 5867.365 | H8: =N8 -> 46234 | I8: 0.28 | J8: =(N8-AF8)/365*C8*I8 -> 350479.45 | K8: 0.08 | L8: =实时行情!$E$7 /( 合约状态!F2 *合约状态!AG2)-1 -> 0.50673868 | M8: {=TRANSPOSE(_xll.DistanceToNearestBarrier(R8,S8,F8,AQ8:BL8,BM8:CH8))} -> -0.0091825518 | N8: 46234 | O8: =BL8-R8 -> 692.53624 | P8: {=INDEX(BM:CH,ROW(), MATCH(H8, AQ8:BL8, 0))} -> 1 | R8: =实时行情!$A$2 -> 46178.464 | S8: =实时行情!E7 -> 8459.631 | T8: {=TRANSPOSE(_xll.ValuateSnowball(实时行情!$D$1,F8,E8,AQ8:BL8,BM8:CH8,CI8:DD8,0,AM8,AG8,AJ8,AK8,AN8,AO8,0,0,0,TRUE,AI8,R8,S8,AA8,AB8,AC8,AL8,"ALL")*C8/F8)} -> 124728.5 | U8: 433.34624 | V8: -0.59667752 | W8: -2341600.7 | X8: 1002399.5 | Y8: -2842068.5 | Z8: -3476895.1 | AA8: 0.021 | AB8: -0.075 | AC8: 0.17 | AD8: 0 | AE8: 8381.95 | AF8: 46142.625 | AG8: 0.7 | AI8: TRUE | AJ8: 1 | AK8: 1 | AL8: FALSE | AM8: 0.08 | AN8: 1 | AO8: 1 | AP8: {=IF(ISERROR(TRANSPOSE(_xll.ValuateSnowball(实时行情!$D$1,F8,AF8,AQ8:BL8,BM8:CH8,CI8:DD8,0,AM8,AG8,AJ8,AK8,AN8,AO8,0,0,0,TRUE,AI8,实时行情!$B$2,实时行情!E8,AA8,AB8,AC8,FALSE,"NPV")*C8/F8)), 0, TRANSPOSE(_xll.ValuateSnowball(实时行情!$D$1,F8,AF8,AQ8:BL8,BM8:CH8,CI8:DD8,0,AM8,AG8,AJ8,AK8,AN8,AO8,0,0,0,TRUE,AI8,实时行情!$B$2,实时行情!$E$8,AA8,AB8,AC8,FALSE,"NPV")*C8/F8))} -> 104908.01 | AQ8: 46234 | AR8: 46265 | AS8: 46295 | AT8: 46325 | AU8: 46356 | AV8: 46387 | AW8: 46416 | AX8: 46444 | AY8: 46477 | AZ8: 46507 | BA8: 46538 | BB8: 46568 | BC8: 46598 | BD8: 46630 | BE8: 46660 | BF8: 46689 | BG8: 46721 | BH8: 46752 | BI8: 46776 | BJ8: 46812 | BK8: 46843 | BL8: 46871 | BM8: 1 | BN8: 0.995 | BO8: 0.99 | BP8: 0.985 | BQ8: 0.98 | BR8: 0.975 | BS8: 0.97 | BT8: 0.965 | BU8: 0.96 | BV8: 0.955 | BW8: 0.95 | BX8: 0.945 | BY8: 0.94 | BZ8: 0.935 | CA8: 0.93 | CB8: 0.925 | CC8: 0.92 | CD8: 0.915 | CE8: 0.91 | CF8: 0.905 | CG8: 0.9 | CH8: 0.895 | CI8: 0.28 | CJ8: 0.28 | CK8: 0.28 | CL8: 0.28 | CM8: 0.28 | CN8: 0.28 | CO8: 0.28 | CP8: 0.28 | CQ8: 0.28 | CR8: 0.28 | CS8: 0.08 | CT8: 0.08 | CU8: 0.08 | CV8: 0.08 | CW8: 0.08 | CX8: 0.08 | CY8: 0.08 | CZ8: 0.08 | DA8: 0.08 | DB8: 0.08 | DC8: 0.08 | DD8: 0.08
A9: 27 | B9: DCN | C9: =25000000*0.79 -> 19750000 | D9: 000852.SH | E9: 46142.625 | F9: 8381.95 | G9: =F9*AG9 -> 5867.365 | H9: =N9 -> 46234 | L9: =实时行情!$E$7 /( 合约状态!F3 *合约状态!AG3)-1 -> 0.50673868 | M9: {=TRANSPOSE(_xll.DistanceToNearestBarrier(R9,S9,F9,AQ9:BL9,BM9:CH9))} -> -0.0091825518 | N9: 46234 | O9: =BL9-R9 -> 692.53624 | P9: {=INDEX(BM:CH,ROW(), MATCH(H9, AQ9:BL9, 0))} -> 1 | R9: =实时行情!$A$2 -> 46178.464 | S9: =实时行情!E7 -> 8459.631 | T9: {=TRANSPOSE(_xll.ValuatePhoenix(实时行情!$D$1,"UP_OUT",F9,E9,CI9:DF9,DG9:ED9,AQ9:BL9,BM9:CH9,AH9,AG9,AI9,AJ9,AK9,AO9,AN9,0,0,R9,S9,AA9,AB9,AC9,AL9,"ALL"))*C9/F9} -> 41898.091 | U9: 444.85907 | V9: -0.94285901 | W9: -7969439 | X9: 1478799.9 | Y9: -10669669 | Z9: -6472407.7 | AA9: 0.021 | AB9: -0.055 | AC9: 0.16 | AD9: 0 | AE9: 8381.95 | AF9: 46142.625 | AG9: 0.7 | AH9: 0.75 | AI9: FALSE | AJ9: 1 | AK9: 1 | AL9: FALSE | AN9: 1 | AO9: 1 | AP9: {=IF(ISERROR(TRANSPOSE(_xll.ValuatePhoenix(实时行情!$D$1,"UP_OUT",F9,E9,CI9:DF9,DG9:ED9,AQ9:BL9,BM9:CH9,AH9,AG9,AI9,AJ9,AK9,AO9,AN9,0,0,实时行情!B2,实时行情!E8,AA9,AB9,AC9,AL9,"NPV")*C9/F9)), 0, TRANSPOSE(_xll.ValuatePhoenix(实时行情!$D$1,"UP_OUT",F9,E9,CI9:DF9,DG9:ED9,AQ9:BL9,BM9:CH9,AH9,AG9,AI9,AJ9,AK9,AO9,AN9,0,0,实时行情!B2,实时行情!E8,AA9,AB9,AC9,AL9,"NPV")*C9/F9))} -> 20186.27 | AQ9: 46234 | AR9: 46265 | AS9: 46295 | AT9: 46325 | AU9: 46356 | AV9: 46387 | AW9: 46416 | AX9: 46444 | AY9: 46477 | AZ9: 46507 | BA9: 46538 | BB9: 46568 | BC9: 46598 | BD9: 46630 | BE9: 46660 | BF9: 46689 | BG9: 46721 | BH9: 46752 | BI9: 46776 | BJ9: 46812 | BK9: 46843 | BL9: 46871 | BM9: 1 | BN9: 0.995 | BO9: 0.99 | BP9: 0.985 | BQ9: 0.98 | BR9: 0.975 | BS9: 0.97 | BT9: 0.965 | BU9: 0.96 | BV9: 0.955 | BW9: 0.95 | BX9: 0.945 | BY9: 0.94 | BZ9: 0.935 | CA9: 0.93 | CB9: 0.925 | CC9: 0.92 | CD9: 0.915 | CE9: 0.91 | CF9: 0.905 | CG9: 0.9 | CH9: 0.895 | CI9: 46171 | CJ9: 46203 | CK9: 46234 | CL9: 46265 | CM9: 46295 | CN9: 46325 | CO9: 46356 | CP9: 46387 | CQ9: 46416 | CR9: 46444 | CS9: 46477 | CT9: 46507 | CU9: 46538 | CV9: 46568 | CW9: 46598 | CX9: 46630 | CY9: 46660 | CZ9: 46689 | DA9: 46721 | DB9: 46752 | DC9: 46776 | DD9: 46812 | DE9: 46843 | DF9: 46871 | DG9: 0.007 | DH9: 0.007 | DI9: 0.007 | DJ9: 0.007 | DK9: 0.007 | DL9: 0.007 | DM9: 0.007 | DN9: 0.007 | DO9: 0.007 | DP9: 0.007 | DQ9: 0.007 | DR9: 0.007 | DS9: 0.007 | DT9: 0.007 | DU9: 0.007 | DV9: 0.007 | DW9: 0.007 | DX9: 0.007 | DY9: 0.007 | DZ9: 0.007 | EA9: 0.007 | EB9: 0.007 | EC9: 0.007 | ED9: 0.007
A10: 20 | B10: 早利雪球 | C10: 22000000 | D10: 000852.SH | E10: 46139.625 | F10: 8338.73 | G10: =F10*AG10 -> 5420.1745 | H10: =N10 -> 46230 | I10: {=INDEX(CI:DD,ROW(), MATCH(H10, AQ10:BL10, 0))} -> 0.26501969 | J10: =(N10-AF10)/365*C10*I10 -> 1443631.2 | K10: 0.08 | L10: =实时行情!$E$7 /( 合约状态!F10 *合约状态!AG10)-1 -> 0.56076728 | M10: {=TRANSPOSE(_xll.DistanceToNearestBarrier(R10,S10,F10,AQ10:BL10,BM10:CH10))} -> -0.014291522 | N10: 46230 | O10: =BL10-R10 -> 691.53624 | P10: {=INDEX(BM:CH,ROW(), MATCH(H10, AQ10:BL10, 0))} -> 1 | R10: =实时行情!$A$2 -> 46178.464 | S10: =实时行情!E7 -> 8459.631 | T10: {=TRANSPOSE(_xll.ValuateSnowball(实时行情!$D$1,F10,E10,AQ10:BL10,BM10:CH10,CI10:DD10,0,AM10,AG10,AJ10,AK10,AN10,AO10,0,0,0,TRUE,AI10,R10,S10,AA10,AB10,AC10,AL10,"ALL")*C10/F10)} -> 643858.8 | U10: 1624.2659 | V10: -2.373863 | W10: -13655043 | X10: 4145007.3 | Y10: -13860527 | Z10: -14141000 | AA10: 0.021 | AB10: -0.08751 | AC10: 0.17 | AD10: 0 | AE10: 8338.73 | AF10: 46139.625 | AG10: 0.65 | AI10: TRUE | AJ10: 1 | AK10: 1 | AL10: FALSE | AM10: 0.08 | AN10: 1 | AO10: 1 | AP10: {=IF(ISERROR(TRANSPOSE(_xll.ValuateSnowball(实时行情!$D$1,F10,AF10,AQ10:BL10,BM10:CH10,CI10:DD10,0,AM10,AG10,AJ10,AK10,AN10,AO10,0,0,0,TRUE,AI10,实时行情!$B$2,实时行情!E8,AA10,AB10,AC10,FALSE,"NPV")*C10/F10)), 0, TRANSPOSE(_xll.ValuateSnowball(实时行情!$D$1,F10,AF10,AQ10:BL10,BM10:CH10,CI10:DD10,0,AM10,AG10,AJ10,AK10,AN10,AO10,0,0,0,TRUE,AI10,实时行情!$B$2,实时行情!$E$8,AA10,AB10,AC10,FALSE,"NPV")*C10/F10))} -> 568590.54 | AQ10: 46230 | AR10: 46261 | AS10: 46293 | AT10: 46322 | AU10: 46353 | AV10: 46384 | AW10: 46414 | AX10: 46444 | AY10: 46475 | AZ10: 46504 | BA10: 46534 | BB10: 46566 | BC10: 46595 | BD10: 46626 | BE10: 46657 | BF10: 46687 | BG10: 46720 | BH10: 46748 | BI10: 46776 | BJ10: 46811 | BK10: 46839 | BL10: 46870 | BM10: 1 | BN10: 1 | BO10: 1 | BP10: 1 | BQ10: 1 | BR10: 1 | BS10: 1 | BT10: 1 | BU10: 1 | BV10: 1 | BW10: 1 | BX10: 1 | BY10: 1 | BZ10: 1 | CA10: 1 | CB10: 1 | CC10: 1 | CD10: 1 | CE10: 1 | CF10: 1 | CG10: 1 | CH10: 1 | CI10: 0.26501969 | CJ10: 0.26501969 | CK10: 0.26501969 | CL10: 0.26501969 | CM10: 0.26501969 | CN10: 0.26501969 | CO10: 0.26501969 | CP10: 0.26501969 | CQ10: 0.26501969 | CR10: 0.26501969 | CS10: 0.08 | CT10: 0.08 | CU10: 0.08 | CV10: 0.08 | CW10: 0.08 | CX10: 0.08 | CY10: 0.08 | CZ10: 0.08 | DA10: 0.08 | DB10: 0.08 | DC10: 0.08 | DD10: 0.08
A11: 19 | B11: 早利雪球 | C11: 23000000 | D11: 000852.SH | E11: 46111.625 | F11: 7767.9297 | G11: =F11*AG11 -> 5437.5508 | H11: =N11 -> 46203 | I11: {=INDEX(CI:DD,ROW(), MATCH(H11, AQ11:BL11, 0))} -> 0.33 | J11: =(N11-AF11)/365*C11*I11 -> 1900099.3 | K11: 0.1 | L11: =实时行情!$E$7 /( 合约状态!F11 *合约状态!AG11)-1 -> 0.55577967 | M11: {=TRANSPOSE(_xll.DistanceToNearestBarrier(R11,S11,F11,AQ11:BL11,BM11:CH11))} -> -0.081764949 | N11: 46203 | O11: =BL11-R11 -> 663.53624 | P11: {=INDEX(BM:CH,ROW(), MATCH(H11, AQ11:BL11, 0))} -> 1 | R11: =实时行情!$A$2 -> 46178.464 | S11: =实时行情!E7 -> 8459.631 | T11: {=TRANSPOSE(_xll.ValuateSnowball(实时行情!$D$1,F11,E11,AQ11:BL11,BM11:CH11,CI11:DD11,0,AM11,AG11,AJ11,AK11,AN11,AO11,0,0,0,TRUE,AI11,R11,S11,AA11,AB11,AC11,AL11,"ALL")*C11/F11)} -> 1848652.5 | U11: 286.45799 | V11: -1.413994 | W11: -1995780.9 | X11: 2276016.8 | Y11: -2400630.8 | Z11: -1082657.6 | AA11: 0.021 | AB11: -0.0746 | AC11: 0.179 | AD11: 0 | AE11: 7767.93 | AF11: 46111.625 | AG11: 0.7 | AI11: TRUE | AJ11: 1 | AK11: 1 | AL11: FALSE | AM11: 0.1 | AN11: 1 | AO11: 1 | AP11: {=IF(ISERROR(TRANSPOSE(_xll.ValuateSnowball(实时行情!$D$1,F11,AF11,AQ11:BL11,BM11:CH11,CI11:DD11,0,AM11,AG11,AJ11,AK11,AN11,AO11,0,0,0,TRUE,AI11,实时行情!$B$2,实时行情!E8,AA11,AB11,AC11,FALSE,"NPV")*C11/F11)), 0, TRANSPOSE(_xll.ValuateSnowball(实时行情!$D$1,F11,AF11,AQ11:BL11,BM11:CH11,CI11:DD11,0,AM11,AG11,AJ11,AK11,AN11,AO11,0,0,0,TRUE,AI11,实时行情!$B$2,实时行情!$E$8,AA11,AB11,AC11,FALSE,"NPV")*C11/F11))} -> 1830443 | AQ11: 46203 | AR11: 46233 | AS11: 46265 | AT11: 46295 | AU11: 46325 | AV11: 46356 | AW11: 46386 | AX11: 46416 | AY11: 46444 | AZ11: 46476 | BA11: 46507 | BB11: 46538 | BC11: 46568 | BD11: 46598 | BE11: 46629 | BF11: 46660 | BG11: 46689 | BH11: 46721 | BI11: 46751 | BJ11: 46776 | BK11: 46812 | BL11: 46842 | BM11: 1 | BN11: 1 | BO11: 1 | BP11: 1 | BQ11: 1 | BR11: 1 | BS11: 1 | BT11: 1 | BU11: 1 | BV11: 1 | BW11: 1 | BX11: 1 | BY11: 1 | BZ11: 1 | CA11: 1 | CB11: 1 | CC11: 1 | CD11: 1 | CE11: 1 | CF11: 1 | CG11: 1 | CH11: 1 | CI11: 0.33 | CJ11: 0.33 | CK11: 0.33 | CL11: 0.33 | CM11: 0.33 | CN11: 0.33 | CO11: 0.33 | CP11: 0.33 | CQ11: 0.33 | CR11: 0.33 | CS11: 0.1 | CT11: 0.1 | CU11: 0.1 | CV11: 0.1 | CW11: 0.1 | CX11: 0.1 | CY11: 0.1 | CZ11: 0.1 | DA11: 0.1 | DB11: 0.1 | DC11: 0.1 | DD11: 0.1

Sheet 实时行情
A1: 实时观察 | B1: 上一交易日 | D1: D:\Quotation\China | J1: GREEKS | K1: NPV | L1: DELTA | M1: GAMMA | N1: THETA
A2: =IF(NOW()>TODAY()+0.625, TODAY()+0.625, NOW()) -> 46178.464 | B2: {=_xll.GetNextBusinessDate(D1,TODAY(),-1)+0.625} -> 46177.625 | J2: VALUE | K2: =G12 -> 1954915.4 | L2: =G23 -> 71327046 | M2: =G25 -> -8145248.8 | N2: =G27 -> 86531.187
J3: PECENTAGE | K3: =K2/($G$16+$G$17) -> 0.0127298 | L3: =L2/($G$16+$G$17) -> 0.4644595 | M3: =M2/($G$16+$G$17) -> -0.053039323 | N3: =N2/($G$16+$G$17) -> 0.00056346414
A5: 标的 | B5: 中证 50 | C5: 沪深300 | D5: 中证500 | E5: 中证1000
B6: 000016.SH | C6: 000300.SH | D6: 000905.SH | E6: 000852.SH
A7: 当前点位 | B7: =RTD("em.rtq",,B6,"NOW") -> 2897.189 | C7: =RTD("em.rtq",,C6,"NOW") -> 4903.604 | D7: =RTD("em.rtq",,D6,"NOW") -> 8360.428 | E7: =RTD("em.rtq",,E6,"NOW") -> 8459.631
A8: 昨日收盘 | B8: {=[1]!EM_I_DQ_CLOSE(B6,实时行情!$B$2)} -> 2891.3488 | C8: {=[1]!EM_I_DQ_CLOSE(C6,实时行情!$B$2)} -> 4904.7454 | D8: {=[1]!EM_I_DQ_CLOSE(D6,实时行情!$B$2)} -> 8356.7444 | E8: {=[1]!EM_I_DQ_CLOSE(E6,实时行情!$B$2)} -> 8420.0946
A9: 存续估值 | G9: 合计
A11: 昨日估值 | B11: =SUMIF(合约状态!$D:$D,B6,合约状态!$AP:$AP) -> 0 | C11: =SUMIF(合约状态!$D:$D,C6,合约状态!$AP:$AP) -> 0 | D11: =SUMIF(合约状态!$D:$D,D6,合约状态!$AP:$AP) -> 0 | E11: =SUMIF(合约状态!$D:$D,E6,合约状态!$AP:$AP)+ SUMIF(合约状态!$D:$D,E6,合约状态!$AD:$AD) -> 1565254.2 | G11: =SUM(B11:E11) -> 1565254.2
A12: 当日估值 | B12: =SUMIF(合约状态!$D:$D,B6,合约状态!$T:$T) -> 0 | C12: =SUMIF(合约状态!$D:$D,C6,合约状态!$T:$T) -> 0 | D12: =SUMIF(合约状态!$D:$D,D6,合约状态!$T:$T) -> 0 | E12: =SUMIF(合约状态!$D:$D,E6,合约状态!$T:$T)+ SUMIF(合约状态!$D:$D,E6,合约状态!$AD:$AD) -> 1954915.4 | G12: =SUM(B12:E12) -> 1954915.4
A13: 当日盈亏 | B13: =B12-B11 -> 0 | C13: =C12-C11 -> 0 | D13: =D12-D11 -> 0 | E13: =E12-E11 -> 389661.22 | G13: =SUM(B13:E13) -> 389661.22
A16: 敲出线上总名本 | B16: =SUMIFS(合约状态!$C:$C,合约状态!$M:$M,"<0",合约状态!$D:$D,B6) -> 0 | C16: =SUMIFS(合约状态!$C:$C,合约状态!$M:$M,"<0",合约状态!$D:$D,C6) -> 0 | D16: =SUMIFS(合约状态!$C:$C,合约状态!$M:$M,"<0",合约状态!$D:$D,D6) -> 0 | E16: =SUMIFS(合约状态!$C:$C,合约状态!$M:$M,"<0",合约状态!$D:$D,E6) -> 69750000 | G16: =SUM(B16:E16) -> 69750000
A17: 敲出线下总名本 | B17: =SUMIFS(合约状态!$C:$C,合约状态!$M:$M,">0",合约状态!$D:$D,B6) -> 0 | C17: =SUMIFS(合约状态!$C:$C,合约状态!$M:$M,">0",合约状态!$D:$D,C6) -> 0 | D17: =SUMIFS(合约状态!$C:$C,合约状态!$M:$M,">0",合约状态!$D:$D,D6) -> 0 | E17: =SUMIFS(合约状态!$C:$C,合约状态!$M:$M,">0",合约状态!$D:$D,E6) -> 83820000 | G17: =SUM(B17:E17) -> 83820000
A19: 标的 | B19: 中证 50 | C19: 沪深300 | D19: 中证500 | E19: 中证1000 | G19: 合计
A20: GREEKS | B20: =SUMIF(合约状态!$D:$D,B6,合约状态!$U:$U) -> 0 | C20: =SUMIF(合约状态!$D:$D,C6,合约状态!$U:$U) -> 0 | D20: =SUMIF(合约状态!$D:$D,D6,合约状态!$U:$U) -> 0 | E20: =SUMIF(合约状态!$D:$D,E6,合约状态!$U:$U) -> 8431.4607
A21: NPV | B21: 0 | C21: 0 | D21: 0 | E21: -975660.29 | G21: -975660.29
A23: DELTACASH | B23: =B20*B7 -> 0 | C23: =C20*C7 -> 0 | D23: =D20*D7 -> 0 | E23: =E20*E7 -> 71327046 | G23: =SUM(B23:E23) -> 71327046
A24: GAMMA | B24: =SUMIF(合约状态!$D:$D,B6,合约状态!$V:$V) -> 0 | C24: =SUMIF(合约状态!$D:$D,C6,合约状态!$V:$V) -> 0 | D24: =SUMIF(合约状态!$D:$D,D6,合约状态!$V:$V) -> 0 | E24: =SUMIF(合约状态!$D:$D,E6,合约状态!$V:$V) -> -11.381553 | F24: （风险度） | G24: =G23/(G16+G17) -> 0.4644595
A25: 1% GAMMACASH | B25: =B24*B7 -> 0 | C25: =C24*C7 -> 0 | D25: =D24*D7 -> 0 | E25: =E24*E7*E7*0.01 -> -8145248.8 | G25: =SUM(B25:E25) -> -8145248.8
A27: 1Day THETA | B27: =SUMIF(合约状态!$D:$D,B6,合约状态!$X:$X) -> 0 | C27: =SUMIF(合约状态!$D:$D,C6,合约状态!$X:$X) -> 0 | D27: =SUMIF(合约状态!$D:$D,D6,合约状态!$X:$X)*1/242 -> 0 | E27: =SUMIF(合约状态!$D:$D,E6,合约状态!$X:$X) / 242 -> 86531.187 | G27: =SUM(B27:E27) -> 86531.187
A29: 已实现收益 | B29: =SUMIF(了结合约!$D:$D,B6,了结合约!$AD:$AD) -> 0 | C29: =SUMIF(了结合约!$D:$D,C6,了结合约!$AD:$AD) -> 0 | D29: =SUMIF(了结合约!$D:$D,D6,了结合约!$AD:$AD) -> 2881016.4 | E29: =SUMIF(了结合约!$D:$D,E6,了结合约!$AD:$AD) -> 13172289 | G29: =SUM(B29:E29) -> 16053305
A30: 累积收益 | B30: =B12+B29 -> 0 | C30: =C12+C29 -> 0 | D30: =D12+D29 -> 2881016.4 | E30: =E12+E29 -> 15127204 | G30: =G12+G29 -> 18008221
A33: 累积估值 | G33: 合计
A34: 昨日估值 | B34: =SUMIF(合约状态!$D:$D,B30,合约状态!$AP:$AP) -> 0 | C34: =SUMIF(合约状态!$D:$D,C30,合约状态!$AP:$AP) -> 0 | D34: =SUMIF(合约状态!$D:$D,D6,合约状态!$AP:$AP) + SUMIF(了结合约!$D:$D,D6,了结合约!$T:$T) -> 2881016.4 | E34: =SUMIF(合约状态!$D:$D,E6,合约状态!$AP:$AP)+ SUMIF(合约状态!$D:$D,E6,合约状态!$AD:$AD) + SUMIF(了结合约!$D:$D,E6,了结合约!$AD:$AD) -> 14737543 | G34: =SUM(B34:E34) -> 17618560
A35: 当日估值 | B35: =SUMIF(合约状态!$D:$D,B30,合约状态!$T:$T) -> 0 | C35: =SUMIF(合约状态!$D:$D,C30,合约状态!$T:$T) -> 0 | D35: =SUMIF(合约状态!$D:$D,D6,合约状态!$T:$T) + SUMIF(了结合约!$D:$D,D6,了结合约!$T:$T) -> 2881016.4 | E35: =SUMIF(合约状态!$D:$D,E6,合约状态!$T:$T)+ SUMIF(合约状态!$D:$D,E6,合约状态!$AD:$AD) + SUMIF(了结合约!$D:$D,E6,了结合约!$AD:$AD) -> 15127204 | G35: =SUM(B35:E35) -> 18008221

Sheet 了结合约
A1: 合约编号 | B1: 合约类型 | C1: 名义本金 | D1: 挂钩标的 | E1: 起息日期 | F1: 期初价格 | G1: 敲入点位 | H1: 临近敲出观察日 | I1: 敲出票息率 | J1: 敲出票息 | K1: 次年票息 | L1: 敲入距离 | M1: 敲出距离 | N1: 下一敲出观察 | O1: 距离合约结束 | P1: 敲出观察比例 | Q1: 了结日期 | R1: DATE | S1: SPOT | T1: NPV | U1: DELTA | V1: GAMMA | W1: VEGA | X1: THETA | Y1: RHO | Z1: RHO Q | AA1: RISK FREE RATE | AB1: CARRY COST | AC1: VOLATILITY | AD1: 已了结收益 | AE1: 期初价格 | AF1: 起息日 | AG1: 敲入障碍价格 | AH1: 派息障碍价格 | AI1: 每日观察敲入 | AJ1: 敲入执行价格 | AK1: 敲入参与率 | AL1: 是否已敲入 | AM1: 红利票息 | AN1: 保证金比例 | AO1: 最大亏损比例 | AP1: 昨日NPV | AQ1: 敲出观察 | AS1: 敲出障碍 | AU1: 派息观察日 | AW1: 派息月息
A2: 18 | B2: 经典雪球 | C2: 11000000 | D2: 000852.SH | E2: 46079.625 | F2: 8490.62 | Q2: 2026.5.26 | T2: 534600 | AA2: 0.021 | AB2: -0.05783 | AC2: 0.19 | AD2: 534600 | AE2: 8490.62 | AF2: 46079.625 | AG2: 0.7 | AI2: TRUE | AJ2: 1 | AK2: 1 | AL2: FALSE | AM2: 0.1971 | AN2: 1 | AO2: 1 | AP2: {=IF(ISERROR(TRANSPOSE(_xll.ValuateSnowball(实时行情!$D$1,F2,AF2,AQ2:BL2,BM2:CH2,CI2:DD2,0,AM2,AG2,AJ2,AK2,AN2,AO2,0,0,0,TRUE,AI2,实时行情!$B$2,实时行情!E8,AA2,AB2,AC2,FALSE,"NPV")*C2/F2)), 0, TRANSPOSE(_xll.ValuateSnowball(实时行情!$D$1,F2,AF2,AQ2:BL2,BM2:CH2,CI2:DD2,0,AM2,AG2,AJ2,AK2,AN2,AO2,0,0,0,TRUE,AI2,实时行情!$B$2,实时行情!$E$8,AA2,AB2,AC2,FALSE,"NPV")*C2/F2))} -> 474357.58 | AQ2: 46168 | AR2: 46199 | AS2: 46230 | AT2: 46260 | AU2: 46293 | AV2: 46321 | AW2: 46352 | AX2: 46384 | AY2: 46413 | AZ2: 46444 | BA2: 46472 | BB2: 46503 | BC2: 46533 | BD2: 46566 | BE2: 46594 | BF2: 46625 | BG2: 46657 | BH2: 46686 | BI2: 46717 | BJ2: 46748 | BK2: 46776 | BL2: 46811 | BM2: 1 | BN2: 1 | BO2: 1 | BP2: 1 | BQ2: 1 | BR2: 1 | BS2: 1 | BT2: 1 | BU2: 1 | BV2: 1 | BW2: 1 | BX2: 1 | BY2: 1 | BZ2: 1 | CA2: 1 | CB2: 1 | CC2: 1 | CD2: 1 | CE2: 1 | CF2: 1 | CG2: 1 | CH2: 1 | CI2: 0.1971 | CJ2: 0.1971 | CK2: 0.1971 | CL2: 0.1971 | CM2: 0.1971 | CN2: 0.1971 | CO2: 0.1971 | CP2: 0.1971 | CQ2: 0.1971 | CR2: 0.1971 | CS2: 0.1971 | CT2: 0.1971 | CU2: 0.1971 | CV2: 0.1971 | CW2: 0.1971 | CX2: 0.1971 | CY2: 0.1971 | CZ2: 0.1971 | DA2: 0.1971 | DB2: 0.1971 | DC2: 0.1971 | DD2: 0.1971
A3: 17 | B3: 早利雪球 | C3: 12000000 | D3: 000852.SH | E3: 46078.625 | F3: 8426.33 | Q3: 2026.5.25 | T3: 987863.01 | AA3: 0.021 | AB3: -0.06378 | AC3: 0.18 | AD3: 1006027.4 | AE3: 8426.33 | AF3: 46078.625 | AG3: 0.7 | AI3: TRUE | AJ3: 1 | AK3: 1 | AL3: FALSE | AM3: 0.05 | AN3: 1 | AO3: 1 | AQ3: 46167 | AR3: 46198 | AS3: 46230 | AT3: 46259 | AU3: 46293 | AV3: 46321 | AW3: 46351 | AX3: 46381 | AY3: 46412 | AZ3: 46443 | BA3: 46471 | BB3: 46503 | BC3: 46532 | BD3: 46563 | BE3: 46594 | BF3: 46624 | BG3: 46657 | BH3: 46685 | BI3: 46716 | BJ3: 46748 | BK3: 46776 | BL3: 46808 | BM3: 1 | BN3: 1 | BO3: 1 | BP3: 1 | BQ3: 1 | BR3: 1 | BS3: 1 | BT3: 1 | BU3: 1 | BV3: 1 | BW3: 1 | BX3: 1 | BY3: 1 | BZ3: 1 | CA3: 1 | CB3: 1 | CC3: 1 | CD3: 1 | CE3: 1 | CF3: 1 | CG3: 1 | CH3: 1 | CI3: 0.34 | CJ3: 0.34 | CK3: 0.34 | CL3: 0.34 | CM3: 0.34 | CN3: 0.34 | CO3: 0.34 | CP3: 0.34 | CQ3: 0.34 | CR3: 0.34 | CS3: 0.05 | CT3: 0.05 | CU3: 0.05 | CV3: 0.05 | CW3: 0.05 | CX3: 0.05 | CY3: 0.05 | CZ3: 0.05 | DA3: 0.05 | DB3: 0.05 | DC3: 0.05 | DD3: 0.05
A4: 14 | B4: 早利雪球 | C4: 10000000 | D4: 000852.SH | E4: 46035.625 | F4: 8287.81 | Q4: 2026.5.13 | T4: 856613.7 | AA4: 0.021 | AB4: -0.0889946 | AC4: 0.185 | AD4: 856613.7 | AE4: 8287.81 | AF4: 46035.625 | AG4: 0.65 | AI4: TRUE | AJ4: 1 | AK4: 1 | AL4: FALSE | AM4: 0.05 | AN4: 0.25 | AO4: 1 | AQ4: 46125 | AR4: 46155 | AS4: 46188 | AT4: 46216 | AU4: 46247 | AV4: 46279 | AW4: 46308 | AX4: 46339 | AY4: 46370 | AZ4: 46400 | BA4: 46433 | BB4: 46461 | BC4: 46490 | BD4: 46520 | BE4: 46552 | BF4: 46581 | BG4: 46612 | BH4: 46643 | BI4: 46673 | BJ4: 46706 | BK4: 46734 | BL4: 46765 | BM4: 1 | BN4: 0.995 | BO4: 0.99 | BP4: 0.985 | BQ4: 0.98 | BR4: 0.975 | BS4: 0.97 | BT4: 0.965 | BU4: 0.96 | BV4: 0.955 | BW4: 0.95 | BX4: 0.945 | BY4: 0.94 | BZ4: 0.935 | CA4: 0.93 | CB4: 0.925 | CC4: 0.92 | CD4: 0.915 | CE4: 0.91 | CF4: 0.905 | CG4: 0.9 | CH4: 0.895 | CI4: 0.2584 | CJ4: 0.2584 | CK4: 0.2584 | CL4: 0.2584 | CM4: 0.2584 | CN4: 0.2584 | CO4: 0.2584 | CP4: 0.2584 | CQ4: 0.2584 | CR4: 0.2584 | CS4: 0.05 | CT4: 0.05 | CU4: 0.05 | CV4: 0.05 | CW4: 0.05 | CX4: 0.05 | CY4: 0.05 | CZ4: 0.05 | DA4: 0.05 | DB4: 0.05 | DC4: 0.05 | DD4: 0.05
A5: 13 | B5: 早利雪球 | C5: 30000000 | D5: 000852.SH | E5: 46031.625 | F5: 8080.6 | Q5: 2026.5.11 | T5: 2757534.2 | AA5: 0.021 | AB5: -0.08111 | AC5: 0.182 | AD5: 2757534.2 | AE5: 8080.6 | AF5: 46031.625 | AG5: 0.65 | AI5: TRUE | AJ5: 1 | AK5: 1 | AL5: FALSE | AM5: 0.05 | AN5: 1 | AO5: 1 | AQ5: 46121 | AR5: 46153 | AS5: 46182 | AT5: 46212 | AU5: 46244 | AV5: 46274 | AW5: 46304 | AX5: 46335 | AY5: 46365 | AZ5: 46398 | BA5: 46433 | BB5: 46455 | BC5: 46486 | BD5: 46517 | BE5: 46548 | BF5: 46577 | BG5: 46608 | BH5: 46639 | BI5: 46671 | BJ5: 46700 | BK5: 46730 | BL5: 46762 | BM5: 1 | BN5: 0.995 | BO5: 0.99 | BP5: 0.985 | BQ5: 0.98 | BR5: 0.975 | BS5: 0.97 | BT5: 0.965 | BU5: 0.96 | BV5: 0.955 | BW5: 0.95 | BX5: 0.945 | BY5: 0.94 | BZ5: 0.935 | CA5: 0.93 | CB5: 0.925 | CC5: 0.92 | CD5: 0.915 | CE5: 0.91 | CF5: 0.905 | CG5: 0.9 | CH5: 0.895 | CI5: 0.275 | CJ5: 0.275 | CK5: 0.275 | CL5: 0.275 | CM5: 0.275 | CN5: 0.275 | CO5: 0.275 | CP5: 0.275 | CQ5: 0.275 | CR5: 0.275 | CS5: 0.05 | CT5: 0.05 | CU5: 0.05 | CV5: 0.05 | CW5: 0.05 | CX5: 0.05 | CY5: 0.05 | CZ5: 0.05 | DA5: 0.05 | DB5: 0.05 | DC5: 0.05 | DD5: 0.05
A6: 16 | B6: 经典雪球 | C6: 21000000 | D6: 000852.SH | E6: 46058.625 | F6: 8091.49 | Q6: 2026.5.6 | T6: 926180.55 | AA6: 0.021 | AB6: -0.08849 | AC6: 0.19 | AD6: 926180.55 | AE6: 8091.49 | AF6: 46058.625 | AG6: 0.65 | AI6: TRUE | AJ6: 1 | AK6: 1 | AL6: FALSE | AM6: 0.1769 | AN6: 1 | AO6: 1 | AQ6: 46148 | AR6: 46178 | AS6: 46209 | AT6: 46239 | AU6: 46272 | AV6: 46303 | AW6: 46331 | AX6: 46363 | AY6: 46392 | AZ6: 46433 | BA6: 46451 | BB6: 46483 | BC6: 46513 | BD6: 46545 | BE6: 46573 | BF6: 46604 | BG6: 46636 | BH6: 46668 | BI6: 46696 | BJ6: 46727 | BK6: 46757 | BL6: 46790 | BM6: 1 | BN6: 1 | BO6: 1 | BP6: 1 | BQ6: 1 | BR6: 1 | BS6: 1 | BT6: 1 | BU6: 1 | BV6: 1 | BW6: 1 | BX6: 1 | BY6: 1 | BZ6: 1 | CA6: 1 | CB6: 1 | CC6: 1 | CD6: 1 | CE6: 1 | CF6: 1 | CG6: 1 | CH6: 1 | CI6: 0.1769 | CJ6: 0.1769 | CK6: 0.1769 | CL6: 0.1769 | CM6: 0.1769 | CN6: 0.1769 | CO6: 0.1769 | CP6: 0.1769 | CQ6: 0.1769 | CR6: 0.1769 | CS6: 0.1769 | CT6: 0.1769 | CU6: 0.1769 | CV6: 0.1769 | CW6: 0.1769 | CX6: 0.1769 | CY6: 0.1769 | CZ6: 0.1769 | DA6: 0.1769 | DB6: 0.1769 | DC6: 0.1769 | DD6: 0.1769
A7: 15 | B7: 早利雪球 | C7: 21000000 | D7: 000852.SH | E7: 46049.625 | F7: 8272.2 | Q7: 2026.4.27 | T7: 1294520.6 | AA7: 0.021 | AB7: -0.074075 | AC7: 0.17 | AD7: 1294520.6 | AE7: 8272.2 | AF7: 46049.625 | AG7: 0.65 | AI7: TRUE | AJ7: 1 | AK7: 1 | AL7: FALSE | AM7: 0.05 | AN7: 1 | AO7: 1 | AQ7: 46139 | AR7: 46169 | AS7: 46202 | AT7: 46230 | AU7: 46261 | AV7: 46293 | AW7: 46322 | AX7: 46353 | AY7: 46384 | AZ7: 46414 | BA7: 46444 | BB7: 46475 | BC7: 46504 | BD7: 46534 | BE7: 46566 | BF7: 46595 | BG7: 46626 | BH7: 46657 | BI7: 46687 | BJ7: 46720 | BK7: 46748 | BL7: 46776 | BM7: 1 | BN7: 1 | BO7: 1 | BP7: 1 | BQ7: 1 | BR7: 1 | BS7: 1 | BT7: 1 | BU7: 1 | BV7: 1 | BW7: 1 | BX7: 1 | BY7: 1 | BZ7: 1 | CA7: 1 | CB7: 1 | CC7: 1 | CD7: 1 | CE7: 1 | CF7: 1 | CG7: 1 | CH7: 1 | CI7: 0.25 | CJ7: 0.25 | CK7: 0.25 | CL7: 0.25 | CM7: 0.25 | CN7: 0.25 | CO7: 0.25 | CP7: 0.25 | CQ7: 0.25 | CR7: 0.25 | CS7: 0.05 | CT7: 0.05 | CU7: 0.05 | CV7: 0.05 | CW7: 0.05 | CX7: 0.05 | CY7: 0.05 | CZ7: 0.05 | DA7: 0.05 | DB7: 0.05 | DC7: 0.05 | DD7: 0.05
A8: 12 | C8: 22000000 | D8: 000852.SH | E8: 46021.625 | F8: 7597.3 | Q8: 2026.3.30 | T8: 1535780.8 | AA8: 0.021 | AB8: -0.07741 | AC8: 0.175 | AD8: 1535780.8 | AE8: 7597.3 | AF8: 46021.625 | AG8: 0.65 | AI8: TRUE | AJ8: 1 | AK8: 1 | AL8: FALSE | AM8: 0.05 | AN8: 1 | AO8: 1 | AQ8: 46111 | AR8: 46142 | AS8: 46171 | AT8: 46203 | AU8: 46233 | AV8: 46265 | AW8: 46295 | AX8: 46325 | AY8: 46356 | AZ8: 46386 | BA8: 46416 | BB8: 46444 | BC8: 46476 | BD8: 46507 | BE8: 46538 | BF8: 46568 | BG8: 46598 | BH8: 46629 | BI8: 46660 | BJ8: 46689 | BK8: 46721 | BL8: 46751 | BM8: 1 | BN8: 1 | BO8: 1 | BP8: 1 | BQ8: 1 | BR8: 1 | BS8: 1 | BT8: 1 | BU8: 1 | BV8: 1 | BW8: 1 | BX8: 1 | BY8: 1 | BZ8: 1 | CA8: 1 | CB8: 1 | CC8: 1 | CD8: 1 | CE8: 1 | CF8: 1 | CG8: 1 | CH8: 1 | CI8: 0.28 | CJ8: 0.28 | CK8: 0.28 | CL8: 0.28 | CM8: 0.28 | CN8: 0.28 | CO8: 0.28 | CP8: 0.28 | CQ8: 0.28 | CR8: 0.28 | CS8: 0.05 | CT8: 0.05 | CU8: 0.05 | CV8: 0.05 | CW8: 0.05 | CX8: 0.05 | CY8: 0.05 | CZ8: 0.05 | DA8: 0.05 | DB8: 0.05 | DC8: 0.05 | DD8: 0.05
A9: 11 | C9: 10000000 | D9: 000852.SH | F9: 7579.38 | Q9: 2026.2.25 | T9: 552328.77 | AA9: 0.021 | AB9: -0.07571 | AC9: 0.175 | AD9: 552328.77 | AE9: 7579.38 | AF9: 46016.625 | AG9: 0.7 | AI9: TRUE | AJ9: 1 | AK9: 1 | AL9: FALSE | AM9: 0.1 | AN9: 1 | AO9: 1 | AQ9: 46078 | AR9: 46106 | AS9: 46139 | AT9: 46167 | AU9: 46198 | AV9: 46230 | AW9: 46259 | AX9: 46293 | AY9: 46321 | AZ9: 46351 | BA9: 46381 | BB9: 46412 | BC9: 46443 | BD9: 46471 | BE9: 46503 | BF9: 46532 | BG9: 46563 | BH9: 46594 | BI9: 46624 | BJ9: 46657 | BK9: 46685 | BL9: 46716 | BM9: 46748 | BN9: 1 | BO9: 1 | BP9: 1 | BQ9: 1 | BR9: 1 | BS9: 1 | BT9: 1 | BU9: 1 | BV9: 1 | BW9: 1 | BX9: 1 | BY9: 1 | BZ9: 1 | CA9: 1 | CB9: 1 | CC9: 1 | CD9: 1 | CE9: 1 | CF9: 1 | CG9: 1 | CH9: 1 | CI9: 1 | CJ9: 1 | CK9: 0.32 | CL9: 0.32 | CM9: 0.32 | CN9: 0.32 | CO9: 0.32 | CP9: 0.32 | CQ9: 0.32 | CR9: 0.32 | CS9: 0.32 | CT9: 0.32 | CU9: 0.32 | CV9: 0.1 | CW9: 0.1 | CX9: 0.1 | CY9: 0.1 | CZ9: 0.1 | DA9: 0.1 | DB9: 0.1 | DC9: 0.1 | DD9: 0.1 | DE9: 0.1 | DF9: 0.1 | DG9: 0.1
A10: 10 | C10: 10000000 | D10: 000905.SH | F10: 7235.46 | Q10: 2026.2.24 | T10: 997830.14 | AA10: 0.021 | AB10: -0.06504 | AC10: 0.16 | AD10: 997830.14 | AE10: 7235.46 | AF10: 45975.625 | AG10: 0.75 | AI10: TRUE | AJ10: 1 | AK10: 1 | AL10: FALSE | AM10: 0.05 | AN10: 1 | AO10: 1 | AQ10: 46077 | AR10: 46097 | AS10: 46126 | AT10: 46156 | AU10: 46188 | AV10: 46217 | AW10: 46248 | AX10: 46279 | AY10: 46309 | AZ10: 46342 | BA10: 46370 | BB10: 46401 | BC10: 46433 | BD10: 46461 | BE10: 46491 | BF10: 46521 | BG10: 46552 | BH10: 46582 | BI10: 46615 | BJ10: 46644 | BK10: 46674 | BL10: 46706 | BM10: 1 | BN10: 1 | BO10: 1 | BP10: 1 | BQ10: 1 | BR10: 1 | BS10: 1 | BT10: 1 | BU10: 1 | BV10: 1 | BW10: 1 | BX10: 1 | BY10: 1 | BZ10: 1 | CA10: 1 | CB10: 1 | CC10: 1 | CD10: 1 | CE10: 1 | CF10: 1 | CG10: 1 | CH10: 1 | CI10: 0.3536 | CJ10: 0.3536 | CK10: 0.3536 | CL10: 0.3536 | CM10: 0.3536 | CN10: 0.3536 | CO10: 0.3536 | CP10: 0.3536 | CQ10: 0.3536 | CR10: 0.3536 | CS10: 0.05 | CT10: 0.05 | CU10: 0.05 | CV10: 0.05 | CW10: 0.05 | CX10: 0.05 | CY10: 0.05 | CZ10: 0.05 | DA10: 0.05 | DB10: 0.05 | DC10: 0.05 | DD10: 0.05
A11: 9 | C11: 10000000 | D11: 000905.SH | F11: 7248.9 | Q11: 2026.2.3 | T11: 924904.11 | AA11: 0.021 | AB11: -0.06087 | AC11: 0.165 | AD11: 924904.11 | AE11: 7248.9 | AF11: 45964.625 | AG11: 0.75 | AI11: TRUE | AJ11: 1 | AK11: 1 | AL11: FALSE | AM11: 0.05 | AN11: 1 | AO11: 1 | AQ11: 46056 | AR11: 46084 | AS11: 46115 | AT11: 46148 | AU11: 46176 | AV11: 46206 | AW11: 46237 | AX11: 46268 | AY11: 46303 | AZ11: 46329 | BA11: 46359 | BB11: 46391 | BC11: 46421 | BD11: 46449 | BE11: 46483 | BF11: 46513 | BG11: 46541 | BH11: 46573 | BI11: 46602 | BJ11: 46633 | BK11: 46668 | BL11: 46694 | BM11: 1 | BN11: 1 | BO11: 1 | BP11: 1 | BQ11: 1 | BR11: 1 | BS11: 1 | BT11: 1 | BU11: 1 | BV11: 1 | BW11: 1 | BX11: 1 | BY11: 1 | BZ11: 1 | CA11: 1 | CB11: 1 | CC11: 1 | CD11: 1 | CE11: 1 | CF11: 1 | CG11: 1 | CH11: 1 | CI11: 0.363 | CJ11: 0.363 | CK11: 0.363 | CL11: 0.363 | CM11: 0.363 | CN11: 0.363 | CO11: 0.363 | CP11: 0.363 | CQ11: 0.363 | CR11: 0.363 | CS11: 0.05 | CT11: 0.05 | CU11: 0.05 | CV11: 0.05 | CW11: 0.05 | CX11: 0.05 | CY11: 0.05 | CZ11: 0.05 | DA11: 0.05 | DB11: 0.05 | DC11: 0.05 | DD11: 0.05
A12: 8 | C12: 10000000 | D12: 000852.SH | F12: 7550.41 | Q12: 2026.1.30 | T12: 930000 | AA12: 0.021 | AB12: -0.08497 | AC12: 0.18 | AD12: 930000 | AE12: 7550.41 | AF12: 45960.625 | AG12: 0.7 | AI12: TRUE | AJ12: 1 | AK12: 1 | AL12: FALSE | AM12: 0.05 | AN12: 1 | AO12: 1 | AQ12: 46052 | AR12: 46080 | AS12: 46111 | AT12: 46142 | AU12: 46171 | AV12: 46203 | AW12: 46233 | AX12: 46265 | AY12: 46295 | AZ12: 46325 | BA12: 46356 | BB12: 46386 | BC12: 46416 | BD12: 46444 | BE12: 46476 | BF12: 46507 | BG12: 46538 | BH12: 46568 | BI12: 46598 | BJ12: 46629 | BK12: 46660 | BL12: 46689 | BM12: 1 | BN12: 0.995 | BO12: 0.99 | BP12: 0.985 | BQ12: 0.98 | BR12: 0.975 | BS12: 0.97 | BT12: 0.965 | BU12: 0.96 | BV12: 0.955 | BW12: 0.95 | BX12: 0.945 | BY12: 0.94 | BZ12: 0.935 | CA12: 0.93 | CB12: 0.925 | CC12: 0.92 | CD12: 0.915 | CE12: 0.91 | CF12: 0.905 | CG12: 0.9 | CH12: 0.895 | CI12: 0.365 | CJ12: 0.365 | CK12: 0.365 | CL12: 0.365 | CM12: 0.365 | CN12: 0.365 | CO12: 0.365 | CP12: 0.365 | CQ12: 0.365 | CR12: 0.365 | CS12: 0.05 | CT12: 0.05 | CU12: 0.05 | CV12: 0.05 | CW12: 0.05 | CX12: 0.05 | CY12: 0.05 | CZ12: 0.05 | DA12: 0.05 | DB12: 0.05 | DC12: 0.05 | DD12: 0.05
A13: 7 | C13: 10000000 | D13: 000852.SH | F13: 7209.61 | Q13: 2026.1.23 | T13: 751134.25 | AA13: 0.021 | AB13: -0.0725 | AC13: 0.17 | AD13: 751134.25 | AE13: 7209.61 | AF13: 45953.625 | AG13: 0.7 | AI13: TRUE | AJ13: 1 | AK13: 1 | AL13: FALSE | AM13: 0.05 | AN13: 1 | AO13: 1 | AQ13: 46045 | AR13: 46077 | AS13: 46104 | AT13: 46135 | AU13: 46167 | AV13: 46196 | AW13: 46226 | AX13: 46258 | AY13: 46288 | AZ13: 46318 | BA13: 46349 | BB13: 46379 | BC13: 46412 | BD13: 46441 | BE13: 46469 | BF13: 46500 | BG13: 46531 | BH13: 46561 | BI13: 46591 | BJ13: 46622 | BK13: 46653 | BL13: 46685 | BM13: 1 | BN13: 0.995 | BO13: 0.99 | BP13: 0.985 | BQ13: 0.98 | BR13: 0.975 | BS13: 0.97 | BT13: 0.965 | BU13: 0.96 | BV13: 0.955 | BW13: 0.95 | BX13: 0.945 | BY13: 0.94 | BZ13: 0.935 | CA13: 0.93 | CB13: 0.925 | CC13: 0.92 | CD13: 0.915 | CE13: 0.91 | CF13: 0.905 | CG13: 0.9 | CH13: 0.895 | CI13: 0.2948 | CJ13: 0.2948 | CK13: 0.2948 | CL13: 0.2948 | CM13: 0.2948 | CN13: 0.2948 | CO13: 0.2948 | CP13: 0.2948 | CQ13: 0.2948 | CR13: 0.2948 | CS13: 0.05 | CT13: 0.05 | CU13: 0.05 | CV13: 0.05 | CW13: 0.05 | CX13: 0.05 | CY13: 0.05 | CZ13: 0.05 | DA13: 0.05 | DB13: 0.05 | DC13: 0.05 | DD13: 0.05
A14: 6 | C14: 10000000 | D14: 000852.SH | F14: 7408.07 | Q14: 2026.1.23 | T14: 1018709.6 | AA14: 0.021 | AB14: -0.077 | AC14: 0.17 | AD14: 1018709.6 | AE14: 7408.07 | AF14: 45923.625 | AG14: 0.7 | AI14: TRUE | AJ14: 1 | AK14: 1 | AL14: FALSE | AM14: 0.05 | AN14: 1 | AO14: 1 | AQ14: 46014 | AR14: 46045 | AS14: 46077 | AT14: 46104 | AU14: 46135 | AV14: 46167 | AW14: 46196 | AX14: 46226 | AY14: 46258 | AZ14: 46288 | BA14: 46318 | BB14: 46349 | BC14: 46379 | BD14: 46412 | BE14: 46441 | BF14: 46469 | BG14: 46500 | BH14: 46531 | BI14: 46561 | BJ14: 46591 | BK14: 46622 | BL14: 46653 | BM14: 1 | BN14: 0.995 | BO14: 0.99 | BP14: 0.985 | BQ14: 0.98 | BR14: 0.975 | BS14: 0.97 | BT14: 0.965 | BU14: 0.96 | BV14: 0.955 | BW14: 0.95 | BX14: 0.945 | BY14: 0.94 | BZ14: 0.935 | CA14: 0.93 | CB14: 0.925 | CC14: 0.92 | CD14: 0.915 | CE14: 0.91 | CF14: 0.905 | CG14: 0.9 | CH14: 0.895 | CI14: 0.3023 | CJ14: 0.3023 | CK14: 0.3023 | CL14: 0.3023 | CM14: 0.3023 | CN14: 0.3023 | CO14: 0.3023 | CP14: 0.3023 | CQ14: 0.3023 | CR14: 0.3023 | CS14: 0.05 | CT14: 0.05 | CU14: 0.05 | CV14: 0.05 | CW14: 0.05 | CX14: 0.05 | CY14: 0.05 | CZ14: 0.05 | DA14: 0.05 | DB14: 0.05 | DC14: 0.05 | DD14: 0.05
A15: 5 | C15: 10000000 | D15: 000852.SH | F15: 7253.81 | Q15: 2025.12.22 | T15: =86160*4 -> 344640 | AA15: 0.021 | AB15: -0.048 | AC15: 0.14 | AD15: =86160*4 -> 344640 | AE15: 7253.81 | AF15: 45890 | AG15: 0.75 | AI15: TRUE | AJ15: 1 | AK15: 1 | AL15: FALSE | AM15: 0 | AN15: 1 | AO15: 1 | AQ15: 45982 | AR15: 46013 | AS15: 46043 | AT15: 46077 | AU15: 46104 | AV15: 46133 | AW15: 46163 | AX15: 46195 | AY15: 46224 | AZ15: 46255 | BA15: 46286 | BB15: 46316 | BC15: 46349 | BD15: 46377 | BE15: 46408 | BF15: 46440 | BG15: 46468 | BH15: 46498 | BI15: 46528 | BJ15: 46559 | BK15: 46589 | BL15: 46622 | BM15: 1 | BN15: 0.995 | BO15: 0.99 | BP15: 0.985 | BQ15: 0.98 | BR15: 0.975 | BS15: 0.97 | BT15: 0.965 | BU15: 0.96 | BV15: 0.955 | BW15: 0.95 | BX15: 0.945 | BY15: 0.94 | BZ15: 0.935 | CA15: 0.93 | CB15: 0.925 | CC15: 0.92 | CD15: 0.915 | CE15: 0.91 | CF15: 0.905 | CG15: 0.9 | CH15: 0.895 | CI15: 45922 | CJ15: 45951 | CK15: 45982 | CL15: 46013 | CM15: 46043 | CN15: 46077 | CO15: 46104 | CP15: 46133 | CQ15: 46163 | CR15: 46195 | CS15: 46224 | CT15: 46255 | CU15: 46286 | CV15: 46316 | CW15: 46349 | CX15: 46377 | CY15: 46408 | CZ15: 46440 | DA15: 46468 | DB15: 46498 | DC15: 46528 | DD15: 46559 | DE15: 46589 | DF15: 46622 | DG15: 0.0086 | DH15: 0.0086 | DI15: 0.0086 | DJ15: 0.0086 | DK15: 0.0086 | DL15: 0.0086 | DM15: 0.0086 | DN15: 0.0086 | DO15: 0.0086 | DP15: 0.0086 | DQ15: 0.0086 | DR15: 0.0086 | DS15: 0.0086 | DT15: 0.0086 | DU15: 0.0086 | DV15: 0.0086 | DW15: 0.0086 | DX15: 0.0086 | DY15: 0.0086 | DZ15: 0.0086 | EA15: 0.0086 | EB15: 0.0086 | EC15: 0.0086 | ED15: 0.0086 | EE15: 0.8
A16: 4 | C16: 10000000 | D16: 000905.SH | F16: 6357.38 | Q16: 2025.11.6 | T16: 479268.49 | AD16: 479268.49 | AE16: 6357.38 | AF16: 45875
A17: 3 | C17: 10000000 | D17: 000905.SH | F17: 6312.47 | Q17: 2025.10.29 | T17: 479013.7 | AD17: 479013.7 | AE17: 6312.47 | AF17: 45867
A18: 2 | C18: 10000000 | D18: 000852.SH | F18: 6706.61 | Q18: 2025.10.27 | T18: 329767.12 | AD18: 329767.12 | AE18: 6706.61 | AF18: 45863
A19: 1 | C19: 10000000 | D19: 000852.SH | F19: 6535.26 | Q19: 2025.10.20 | T19: 334458.97 | AD19: 334452.05 | AE19: 6535.26 | AF19: 45856
AB24: 25年 合计 | AC24: =SUM(AD15:AD19) -> 1967141.4
AB25: 26年合计 | AC25: =SUM(AD2:AD14) -> 14086164
AB26: 合计 | AC26: =SUM(AD1:AD27) -> 16053305

Sheet 历史行情
A1: =[1]!EM_HQ_N("000016.SH,000300.SH,000905.SH,000852.SH","CLOSE","2025-07-18","N","Period=1,AdjustFlag=1,Type=1,CalendarType=1,Market=ALL,DealType=1,Layout1=0,Layout2=0,Order=0,DateType=0") -> 历史行情 | L1: 估值总和
B2: 000016.SH | C2: 000300.SH | D2: 000905.SH | E2: 000852.SH
B3: 上证50 | C3: 沪深300 | D3: 中证500 | E3: 中证1000 | F3: 存续合约估值 | G3: 估值
B4: 收盘价 | C4: 收盘价 | D4: 收盘价 | E4: 收盘价 | G4: 000016.SH | H4: 000300.SH | I4: 000905.SH | J4: 000852.SH
A5: 45856 | B5: 2764.516 | C5: 4058.5486 | D5: 6099.6104 | E5: 6552.0741 | G5: 0 | H5: 0 | I5: 0 | J5: 10514.504 | L5: 10514.504
A6: 45859 | B6: 2772.2385 | C6: 4085.6072 | D6: 6161.3086 | E6: 6612.2589 | G6: 0 | H6: 0 | I6: 0 | J6: 50363.244 | L6: 50363.244
A7: 45860 | B7: 2792.1823 | C7: 4118.9582 | D7: 6213.4072 | E7: 6637.1035 | G7: 0 | H7: 0 | I7: 0 | J7: 68300.47 | L7: 68300.47
A8: 45861 | B8: 2801.2002 | C8: 4119.7685 | D8: 6196.7577 | E8: 6607.22 | G8: 0 | H8: 0 | I8: 0 | J8: 57068.686 | L8: 57068.686
A9: 45862 | B9: 2812.4428 | C9: 4149.0368 | D9: 6293.5984 | E9: 6701.12 | G9: 0 | H9: 0 | I9: 0 | J9: 108276.03 | L9: 108276.03
A10: 45863 | B10: 2795.5127 | C10: 4127.1634 | D10: 6299.5908 | E10: 6706.6098 | G10: 0 | H10: 0 | I10: 0 | J10: 115011.33 | L10: 115011.33
A11: 45866 | B11: 2802.7674 | C11: 4135.8242 | D11: 6323.4198 | E11: 6729.979 | G11: 0 | H11: 0 | I11: 0 | J11: 148096.69 | L11: 148096.69
A12: 45867 | B12: 2808.5917 | C12: 4152.0247 | D12: 6356.1327 | E12: 6773.8843 | G12: 0 | H12: 0 | I12: 43458.519 | J12: 198768.35 | L12: 242226.87
A13: 45868 | B13: 2819.3508 | C13: 4151.2379 | D13: 6314.6873 | E13: 6718.4819 | G13: 0 | H13: 0 | I13: 7792.9122 | J13: 154811.33 | L13: 162604.24
A14: 45869 | B14: 2775.9935 | C14: 4075.5912 | D14: 6226.3432 | E14: 6661.1862 | G14: 0 | H14: 0 | I14: -84127.258 | J14: 103739.49 | L14: 19612.23
A15: 45870 | B15: 2754.1302 | C15: 4054.9286 | D15: 6213.2014 | E15: 6670.472 | G15: 0 | H15: 0 | I15: -94039.447 | J15: 123482.34 | L15: 29442.889
A16: 45873 | B16: 2769.3934 | C16: 4070.7023 | D16: 6261.7313 | E16: 6739.6936 | G16: 0 | H16: 0 | I16: -31952.567 | J16: 202540.64 | L16: 170588.07
... A216: 46177 | B216: 2891.3488 | C216: 4904.7454 | D216: 8356.7444 | E216: 8420.0946 | G216: 0 | H216: 0 | I216: 2881016.4 | J216: 14718267 | L216: 17618563
A218: 数据来源：妙想Choice

Sheet Sheet2
A1: 存量合约估值情景分析
B2: 悲观（7000） | C2: 横盘（8304） | D2: 乐观（9000）
A3: 当前 | B3: 14056409 | C3: 14056409 | D3: 14056409
A4: 46226.625 | B4: -4421687.6 | C4: 21089486 | D4: 23035498
A5: 46316.625 | B5: 186715.08 | C5: 28749317 | D5: 31448878
A6: 46406.625 | B6: 5515937 | C6: 26385042 | D6: 30418136
A7: 46470.59 | B7: 12668890 | C7: 21654656 | D7: 21444355
